{
  "schema_version": 9,
  "id": "d376b5ec15290e82a6",
  "slug": "vance-says-talks-with-iranian-officials-set-good-foundation-for-a-deal-t-d376b5ec",
  "level": "B1",
  "title": "Vance says talks with Iranian officials set 'good foundation' for a deal to end war",
  "description": "U.S. Vice-President JD Vance on Monday said his lengthy talks with senior Iranian officials in Switzerland created a \"good foundation for a successful final deal\" as they negotiate bringing a permanent end to the war that the U.S. and Israel began in late February.",
  "text": "U.S. Vice-President JD Vance on Monday said his lengthy talks with senior Iranian officials in Switzerland created a \"good foundation for a successful final deal\" as they negotiate bringing a permanent end to the war that the U.S. and Israel began in late February. U.S. Vice-President JD Vance says the U.S. might agree to unfreeze Iranian assets for purchases of U.S. soy, corn and wheat. U.S. Vice-President JD Vance on Monday said his lengthy talks with senior Iranian officials in Switzerland created a \"good foundation for a successful final deal\" as they negotiate bringing a permanent end to the war that the U.S. and Israel began in late February. Vance and U.S. officials claimed progress on multiple fronts, including the establishment of \"mechanisms\" to ensure the Strait of Hormuz, a vital waterway for global energy shipments, stays open.",
  "thai_text": "ข่าวนี้มาจาก CBC News อยู่ในหมวดข่าวต่างประเทศ และถูกเรียบเรียงเป็นระดับ B1. เนื้อหาข่าวคือ รองประธาน JD Vance ในวันจันทร์ที่ผ่านมาบอกว่า การเจรจาที่ยาวนานของเขากับเจ้าหน้าที่ระดับสูงของอิหร่านในสวิตเซอร์แลนด์ สร้าง \"พื้นฐานที่ดีสำหรับข้อตกลงสุดท้ายที่ประสบความสําเร็จ\" ขณะที่พวกเขาเจรจาจะเสร็จสิ้นสงครามที่สหรัฐอเมริกาและอิสราเอลเริ่มในช่วงปลายเดือนกุมภาพันธ์. รองประธาน JD Vance บอกว่าสหรัฐอเมริกาอาจยอมรับที่จะยกเลิกทรัพย์สินของอิหร่าน สำหรับการซื้อของเอเชีย, ข้าวข้าวและข้าวข้าวของสหรัฐอเมริกา. รองประธาน JD Vance ในวันจันทร์ที่ผ่านมาบอกว่า การเจรจาที่ยาวนานของเขากับเจ้าหน้าที่ระดับสูงของอิหร่านในสวิตเซอร์แลนด์ สร้าง \"พื้นฐานที่ดีสำหรับข้อตกลงสุดท้ายที่ประสบความสําเร็จ\" ขณะที่พวกเขาเจรจาจะเสร็จสิ้นสงครามที่สหรัฐอเมริกาและอิสราเอลเริ่มในช่วงปลายเดือนกุมภาพันธ์. วานส์ และเจ้าหน้าที่สหรัฐอเมริกา ยืนยันว่า มีความก้าวหน้าในหลายด้าน รวมถึงการจัดตั้ง \"กลไก\" เพื่อประกันว่า สะเก็ตออร์มูซ ซึ่งเป็นเส้นทางน้ําที่สําคัญสำหรับการส่งพลังงานทั่วโลก จะถูกเปิดให้บริการ.",
  "word_translations": {
    "a": "",
    "agree": "เห็นด้วย",
    "and": "และ",
    "as": "ขณะที่",
    "assets": "",
    "began": "",
    "bringing": "นำมา",
    "claimed": "กล่าวอ้าง",
    "corn": "",
    "created": "",
    "deal": "ข้อตกลง",
    "end": "จบ",
    "energy": "พลังงาน",
    "ensure": "ทำให้มั่นใจ",
    "establishment": "",
    "february": "กุมภาพันธ์",
    "final": "สุดท้าย",
    "for": "สำหรับ",
    "foundation": "ฐานราก",
    "fronts": "ด้านหน้า",
    "global": "ระดับโลก",
    "good": "ดี",
    "his": "ของเขา",
    "hormuz": "",
    "in": "ใน",
    "including": "รวมทั้ง",
    "iranian": "",
    "israel": "",
    "jd": "",
    "late": "ช้า",
    "lengthy": "",
    "mechanisms": "",
    "might": "อาจ",
    "monday": "วันจันทร์",
    "multiple": "",
    "negotiate": "เจรจาต่อรอง",
    "of": "ของ",
    "officials": "เจ้าหน้าที่",
    "on": "บน",
    "open": "เปิด",
    "permanent": "ถาวร",
    "progress": "ความคืบหน้า",
    "purchases": "",
    "s": "",
    "said": "",
    "says": "พูด",
    "senior": "อาวุโส",
    "shipments": "",
    "soy": "",
    "stays": "อยู่",
    "strait": "",
    "successful": "ประสบความสำเร็จ",
    "switzerland": "",
    "talks": "พูดคุย",
    "that": "ที่",
    "the": "ที่",
    "they": "พวกเขา",
    "to": "ถึง",
    "u": "",
    "unfreeze": "",
    "vance": "",
    "vice-president": "",
    "vital": "สำคัญยิ่ง",
    "war": "สงคราม",
    "waterway": "",
    "wheat": "",
    "with": "กับ"
  },
  "category": "World",
  "provider": "CBC News",
  "word_pos": {
    "a": "det.",
    "agree": "n.",
    "and": "conj.",
    "as": "n.",
    "assets": "n.",
    "began": "n.",
    "bringing": "v.",
    "claimed": "v.",
    "corn": "n.",
    "created": "v.",
    "deal": "adj.",
    "end": "n.",
    "energy": "n.",
    "ensure": "n.",
    "establishment": "n.",
    "february": "n.",
    "final": "adj.",
    "for": "prep.",
    "foundation": "n.",
    "fronts": "n.",
    "global": "adj.",
    "good": "adj.",
    "his": "n.",
    "hormuz": "n.",
    "in": "prep.",
    "including": "v.",
    "iranian": "n.",
    "israel": "n.",
    "jd": "n.",
    "late": "v.",
    "lengthy": "n.",
    "mechanisms": "n.",
    "might": "n.",
    "monday": "n.",
    "multiple": "n.",
    "negotiate": "v.",
    "of": "prep.",
    "officials": "n.",
    "on": "prep.",
    "open": "v.",
    "permanent": "n.",
    "progress": "n.",
    "purchases": "n.",
    "s": "n.",
    "said": "n.",
    "says": "n.",
    "senior": "n.",
    "shipments": "n.",
    "soy": "n.",
    "stays": "n.",
    "strait": "n.",
    "successful": "adj.",
    "switzerland": "n.",
    "talks": "n.",
    "that": "det.",
    "the": "det.",
    "they": "pron.",
    "to": "prep.",
    "u": "n.",
    "unfreeze": "n.",
    "vance": "n.",
    "vice-president": "n.",
    "vital": "adj.",
    "war": "n.",
    "waterway": "n.",
    "wheat": "n.",
    "with": "prep."
  },
  "content_type": "rss news summary",
  "source_url": "https://www.cbc.ca/news/world/iran-u-s-talks-switzerland-9.7243991?cmp=rss",
  "author": "CBC News",
  "published": "2026-06-22T10:16:19+00:00",
  "published_date": "2026-06-22",
  "image": {
    "cache_version": 2,
    "url": "",
    "local_filename": "fallback-d376b5ec1529.svg",
    "image_url": "static/images/fallback-d376b5ec1529.svg",
    "image_local_path": "static/images/fallback-d376b5ec1529.svg",
    "image_source": "Local generated SVG",
    "image_author": "Daily English Reader",
    "image_license": "Project-owned local asset",
    "image_attribution_url": "",
    "image_alt": "Cover image for Vance says talks with Iranian officials set 'good foundation' for a deal to end war",
    "image_query": "World Vance Iranian says talks officials set good",
    "image_relevance_score": 20,
    "image_selected_reason": "No usable free image candidate",
    "image_is_fallback": true,
    "credit": "Daily English Reader",
    "credit_url": ""
  },
  "audio_cache_path": "data/audio/2026-06-22/d376b5ec15290e82a6-b1.wav",
  "generated_at": "2026-06-23T17:43:50.710731+00:00"
}