{
  "schema_version": 9,
  "id": "a849d3decea1762204",
  "slug": "severe-thunderstorm-warning-issued-june-24-at-11-11pm-cdt-until-june-24-a849d3de",
  "level": "A2",
  "title": "Severe Thunderstorm Warning issued June 24 at 11:11PM CDT until June 24 at 11:30PM CDT by NWS Lubbock TX",
  "description": "At 1110 PM CDT, a severe thunderstorm was located 8 miles west of Abernathy, moving east at 20 mph. HAZARD...Ping pong ball size hail and 60 mph wind gusts. SOURCE...Radar indicated. IMPACT...People and animals outdoors will be injured. Expect hail damage to roofs, siding, windows, and vehicles. Expect wind damage to roofs, siding, and trees. Locations impacted include... Lubbock, Abernathy, Hale Center, Shallowater, Cotton Center, Lubbock International Airport, and New Deal.",
  "text": "At 11:10 PM Central Daylight Time, a severe thunderstorm was located 8 miles west of Abernathy, moving east at 20 miles per hour. Hazard, hailstones the size of ping pong balls and 60 miles per hour wind gusts. Source: Radar indicated.\n\nImpact: People and animals outdoors will be injured. Expect hail damage to roofs, siding, windows, and vehicles. Expect wind damage to roofs, siding, and trees.",
  "speech_text": "Severe Thunderstorm Warning issued June 24 at 11:11PM CDT until June 24 at 11:30PM CDT by NWS Lubbock TX.\n\nAt 11:10 PM Central Daylight Time, a severe thunderstorm was located 8 miles west of Abernathy, moving east at 20 miles per hour. Hazard, hailstones the size of ping pong balls and 60 miles per hour wind gusts. Source: Radar indicated.\n\nImpact: People and animals outdoors will be injured. Expect hail damage to roofs, siding, windows, and vehicles. Expect wind damage to roofs, siding, and trees.",
  "thai_text": "ข่าวนี้มาจาก US National Weather Service อยู่ในหมวดสิ่งแวดล้อม และถูกเรียบเรียงเป็นระดับ A2. เนื้อหาข่าวคือ\n\nเวลา 11.10 PM น. เวลากลางวัน มีฝนฟ้าคะนองที่รุนแรง ตั้งอยู่ทางตะวันตก 8 ไมล์์จากอเบอร์เนธี่ เดินทางทางตะวันออกด้วยความเร็ว 20 ไมล์ต่อชั่วโมง์ต่อชั่วโมง. อันตรายหินหินหินขนาดบอลพิงโปง และลมแรง 60 ไมล์ต่อชั่วโมง์ต่อชั่วโมง. แหล่งข่าว: ราดาร์.\n\nผล กระทบ: คนและสัตว์ในพื้นที่กลางแจ้ง จะได้รับบาดเจ็บ. คาดว่าจะเกิดความเสียหายจากฝนฟ้าคะนอง. คาดว่าลมจะทำลายหลังคา หลังคา และต้นไม้.",
  "word_translations": {
    "a": "",
    "abernathy": "",
    "and": "และ",
    "animals": "สัตว์",
    "at": "ที่",
    "balls": "ลูกบอล",
    "be": "เป็น",
    "central": "ศูนย์กลาง",
    "damage": "ความเสียหาย",
    "daylight": "",
    "east": "ทิศตะวันออก",
    "expect": "คาดว่า",
    "gusts": "",
    "hail": "",
    "hailstones": "",
    "hazard": "อันตราย",
    "hour": "ชั่วโมง",
    "impact": "ผลกระทบ",
    "indicated": "",
    "injured": "ได้รับบาดเจ็บ",
    "located": "ตั้งอยู่",
    "miles": "",
    "moving": "การย้าย",
    "of": "ของ",
    "outdoors": "กลางแจ้ง",
    "people": "ผู้คน",
    "per": "ต่อ",
    "ping": "",
    "pm": "",
    "pong": "",
    "radar": "",
    "roofs": "หลังคา",
    "severe": "รุนแรง",
    "siding": "",
    "size": "ขนาด",
    "source": "แหล่งข้อมูล",
    "the": "ที่",
    "thunderstorm": "",
    "time": "เวลา",
    "to": "ถึง",
    "trees": "",
    "vehicles": "",
    "was": "",
    "west": "ตะวันตก",
    "will": "จะ",
    "wind": "ลม",
    "windows": "หน้าต่าง"
  },
  "category": "Environment",
  "provider": "US National Weather Service",
  "word_pos": {
    "a": "det.",
    "abernathy": "n.",
    "and": "conj.",
    "animals": "n.",
    "at": "prep.",
    "balls": "n.",
    "be": "v.",
    "central": "adj.",
    "damage": "n.",
    "daylight": "n.",
    "east": "n.",
    "expect": "v.",
    "gusts": "n.",
    "hail": "n.",
    "hailstones": "n.",
    "hazard": "n.",
    "hour": "n.",
    "impact": "n.",
    "indicated": "v.",
    "injured": "v.",
    "located": "v.",
    "miles": "n.",
    "moving": "v.",
    "of": "prep.",
    "outdoors": "n.",
    "people": "n.",
    "per": "n.",
    "ping": "v.",
    "pm": "n.",
    "pong": "n.",
    "radar": "n.",
    "roofs": "n.",
    "severe": "n.",
    "siding": "v.",
    "size": "v.",
    "source": "n.",
    "the": "det.",
    "thunderstorm": "n.",
    "time": "n.",
    "to": "prep.",
    "trees": "n.",
    "vehicles": "n.",
    "was": "n.",
    "west": "n.",
    "will": "v.",
    "wind": "n.",
    "windows": "n."
  },
  "content_type": "government weather alert",
  "source_url": "https://api.weather.gov/alerts/urn:oid:2.49.0.1.840.0.3403a9be20caa3e9bef1628f8e4cd2d58d43ec93.002.1",
  "author": "National Weather Service",
  "published": "2026-06-25T04:11:00+00:00",
  "published_date": "2026-06-25",
  "image": {
    "cache_version": 2,
    "url": "",
    "local_filename": "fallback-a849d3decea1.svg",
    "image_url": "static/images/fallback-a849d3decea1.svg",
    "image_local_path": "static/images/fallback-a849d3decea1.svg",
    "image_source": "Local generated SVG",
    "image_author": "Daily English Reader",
    "image_license": "Project-owned local asset",
    "image_attribution_url": "",
    "image_alt": "Cover image for Severe Thunderstorm Warning issued June 24 at 11:11PM CDT until June 24 at 11:30PM CDT by NWS Lubbock TX",
    "image_query": "Environment Severe Thunderstorm Warning June CDT NWS Lubbock TX severe thunderstorm warning",
    "image_relevance_score": 20,
    "image_selected_reason": "No usable free image candidate",
    "image_is_fallback": true,
    "credit": "Daily English Reader",
    "credit_url": ""
  },
  "audio_cache_path": "data/audio/2026-06-25/a849d3decea1762204-a2.wav",
  "generated_at": "2026-06-25T04:23:30.874322+00:00"
}