{
  "schema_version": 9,
  "id": "611007ed321e73112c",
  "slug": "canada-s-population-drops-in-first-quarter-of-2026-611007ed",
  "level": "B2",
  "title": "Canada's population drops in first quarter of 2026",
  "description": "Canada's population dipped by about 55,000 people in the first three months of this year, according to new numbers from Statistics Canada, which estimates the population as of April 1 was 41,417,056.",
  "text": "Canada's population dipped by about 55,000 people in the first three months of this year, according to new numbers from Statistics Canada, which estimates the population as of April 1 was 41,417,056. Canada's population dipped by about 55,000 people in the first three months of this year, according to new numbers from Statistics Canada, which estimates the population as of April 1 was 41,417,056. The 0.1 per cent drop reflects a decrease in both immigration and in births compared to deaths, the agency said. There were about 20 per cent fewer permanent immigrants in Canada in the first quarter of this year compared to the same time last year, dropping to 83,149 from 104,210 in 2025. The number of non-permanent residents dropped by more than 117,000, though Statistics Canada cautioned there may be future updates to those initial estimates due to \"shifting international migration policies.\" As well, what the agency calls \"natural increase\" in population — if births outnumber deaths — was, in fact, a decrease as 155 more people died than were born across the country in the first quarter.",
  "thai_text": "ข่าวนี้มาจาก CBC News อยู่ในหมวดธุรกิจและเศรษฐกิจ และถูกเรียบเรียงเป็นระดับ B2. เนื้อหาข่าวคือ ประชากรแคนาดา ลดลงประมาณ 55,000 คนในสามเดือนแรกของปีนี้ ตามจํานวนใหม่จากสถิติแคนาดา ซึ่งประมาณว่าประชากรเมื่อวันที่ 1 เมษายน มี 41,417,056 คน. ประชากรแคนาดา ลดลงประมาณ 55,000 คนในสามเดือนแรกของปีนี้ ตามจํานวนใหม่จากสถิติแคนาดา ซึ่งประมาณว่าประชากรเมื่อวันที่ 1 เมษายน มี 41,417,056 คน. หน่วยงานบอกว่า การลดลง 0.1% แสดงถึงการลดลงทั้งการอพยพและการเกิดเมื่อเทียบกับการตาย. ในไตรมาสแรกของปีนี้ มีผู้อพยพถาวรน้อยกว่าประมาณ 20 เปอร์เซ็นต์ในแคนาดา เมื่อเทียบกับช่วงเดียวกันของปีที่แล้ว ลดลงเป็น 83,149 จาก 104,210 ในปี 2025. จํานวนประชากรที่ไม่ได้อยู่ในระยะยาวลดลงกว่า 117,000 คน แม้ว่าสถิติแคนาดาได้เตือนว่าอาจมีการปรับปรุงในอนาคตของประมาณการแรกเหล่านั้น เพราะ \"การเปลี่ยนแปลงนโยบายการอพยพระหว่างประเทศ\" เช่นเดียวกับสิ่งที่หน่วยงานเรียกว่า \"การเพิ่มประชากรตามธรรมชาติ\" หากเกิดมากกว่าจํานวนผู้เสียชีวิต. เป็นการลดลง เพราะมีผู้เสียชีวิตมากกว่า 155 คนที่เกิดในประเทศในไตรมาสแรก.",
  "word_translations": {
    "a": "",
    "about": "เกี่ยวกับ",
    "according": "ตามข้อมูลจาก",
    "across": "ข้าม",
    "agency": "หน่วยงาน",
    "and": "และ",
    "april": "เมษายน",
    "as": "ขณะที่",
    "be": "เป็น",
    "births": "การเกิด",
    "born": "เกิด",
    "both": "ทั้งคู่",
    "by": "โดย",
    "calls": "เรียก",
    "canada": "แคนาดา",
    "canada's": "",
    "cautioned": "",
    "cent": "ร้อยละ",
    "compared": "",
    "country": "ประเทศ",
    "deaths": "ความตาย",
    "decrease": "ลด",
    "died": "",
    "dipped": "",
    "drop": "หยด",
    "dropped": "",
    "dropping": "ลดลง",
    "due": "เนื่องจาก",
    "estimates": "",
    "fact": "ข้อเท็จจริง",
    "fewer": "",
    "first": "อันดับแรก",
    "from": "จาก",
    "future": "อนาคต",
    "if": "ถ้า",
    "immigrants": "",
    "immigration": "",
    "in": "ใน",
    "increase": "เพิ่มขึ้น",
    "initial": "อักษรย่อ",
    "international": "ระหว่างประเทศ",
    "last": "ล่าสุด",
    "may": "อาจ",
    "migration": "",
    "months": "เดือน",
    "more": "มากกว่า",
    "natural": "เป็นธรรมชาติ",
    "new": "ใหม่",
    "non-permanent": "",
    "number": "ตัวเลข",
    "numbers": "ตัวเลข",
    "of": "ของ",
    "outnumber": "",
    "people": "ผู้คน",
    "per": "ต่อ",
    "permanent": "ถาวร",
    "policies": "",
    "population": "ประชากร",
    "quarter": "หนึ่งในสี่",
    "reflects": "สะท้อน",
    "residents": "ถิ่นที่อยู่",
    "said": "",
    "same": "เดียวกัน",
    "shifting": "กะ",
    "statistics": "",
    "than": "กว่า",
    "the": "ที่",
    "there": "ที่นั่น",
    "this": "นี้",
    "those": "",
    "though": "แม้ว่า",
    "three": "สาม",
    "time": "เวลา",
    "to": "ถึง",
    "updates": "",
    "was": "",
    "well": "ดี",
    "were": "",
    "what": "อะไร",
    "which": "ที่",
    "year": "ปี"
  },
  "category": "Business",
  "provider": "CBC News",
  "word_pos": {
    "a": "det.",
    "about": "prep.",
    "according": "v.",
    "across": "n.",
    "agency": "n.",
    "and": "conj.",
    "april": "n.",
    "as": "n.",
    "be": "v.",
    "births": "n.",
    "born": "n.",
    "both": "n.",
    "by": "prep.",
    "calls": "n.",
    "canada": "n.",
    "canada's": "n.",
    "cautioned": "v.",
    "cent": "n.",
    "compared": "v.",
    "country": "n.",
    "deaths": "n.",
    "decrease": "n.",
    "died": "v.",
    "dipped": "v.",
    "drop": "n.",
    "dropped": "v.",
    "dropping": "v.",
    "due": "n.",
    "estimates": "n.",
    "fact": "n.",
    "fewer": "n.",
    "first": "n.",
    "from": "prep.",
    "future": "n.",
    "if": "conj.",
    "immigrants": "n.",
    "immigration": "n.",
    "in": "prep.",
    "increase": "n.",
    "initial": "adj.",
    "international": "adj.",
    "last": "n.",
    "may": "v.",
    "migration": "n.",
    "months": "n.",
    "more": "n.",
    "natural": "adj.",
    "new": "adj.",
    "non-permanent": "n.",
    "number": "n.",
    "numbers": "n.",
    "of": "prep.",
    "outnumber": "n.",
    "people": "n.",
    "per": "n.",
    "permanent": "n.",
    "policies": "n.",
    "population": "n.",
    "quarter": "n.",
    "reflects": "n.",
    "residents": "n.",
    "said": "n.",
    "same": "n.",
    "shifting": "v.",
    "statistics": "n.",
    "than": "n.",
    "the": "det.",
    "there": "n.",
    "this": "det.",
    "those": "det.",
    "though": "n.",
    "three": "n.",
    "time": "n.",
    "to": "prep.",
    "updates": "n.",
    "was": "n.",
    "well": "n.",
    "were": "n.",
    "what": "n.",
    "which": "pron.",
    "year": "n."
  },
  "content_type": "rss news summary",
  "source_url": "https://www.cbc.ca/news/business/population-drop-first-quarter-2026-9.7238364?cmp=rss",
  "author": "CBC News",
  "published": "2026-06-17T14:58:04+00:00",
  "published_date": "2026-06-17",
  "image": {
    "cache_version": 2,
    "url": "",
    "local_filename": "fallback-611007ed321e.svg",
    "image_url": "static/images/fallback-611007ed321e.svg",
    "image_local_path": "static/images/fallback-611007ed321e.svg",
    "image_source": "Local generated SVG",
    "image_author": "Daily English Reader",
    "image_license": "Project-owned local asset",
    "image_attribution_url": "",
    "image_alt": "Cover image for Canada's population drops in first quarter of 2026",
    "image_query": "Business Canada's canada population drops first quarter",
    "image_relevance_score": 20,
    "image_selected_reason": "No usable free image candidate",
    "image_is_fallback": true,
    "credit": "Daily English Reader",
    "credit_url": ""
  },
  "audio_cache_path": "data/audio/2026-06-17/611007ed321e73112c-b2.wav",
  "generated_at": "2026-06-23T19:00:03.833098+00:00"
}