{
  "fetched_at": "2026-06-25T04:21:24.377467+00:00",
  "candidates": [
    {
      "id": "b76b1f35fe9015c543",
      "provider": "CBC News",
      "title": "Canada finishes 2nd in Group B after 2-1 loss to Switzerland, will play South Africa in knockout game Sunday",
      "description": "Canada’s men lost to Switzerland 2-1 in a sweltering B.C. Place on Wednesday afternoon, ending their hopes of continuing their historic World Cup campaign at home.",
      "url": "https://www.cbc.ca/sports/soccer/worldcup/fifa-canada-world-cup-canada-switzerland-recap-june-24-9.7246842?cmp=rss",
      "category": "Canada",
      "published": "2026-06-24T21:07:57+00:00",
      "author": "CBC News",
      "content_type": "rss news summary",
      "image_url": "",
      "thai_demo": "",
      "provider_key": "rss_cbc-news-canada"
    },
    {
      "id": "1d6d1b3e6d60a8ad93",
      "provider": "CBC News",
      "title": "Halifax-bound Air Canada flight diverted to Boston after captain experiences medical issue",
      "description": "AC7664 was enroute from Newark to Halifax on Wednesday afternoon. The captain experienced a medical issue during the flight and it was diverted to Boston. Air Canada says it is working to help its 61 customers who were on the plane make new travel arrangements.",
      "url": "https://www.cbc.ca/news/canada/nova-scotia/flight-to-halifax-diverted-boston-captain-emedical-issue-9.7248001?cmp=rss",
      "category": "Canada",
      "published": "2026-06-24T22:52:41+00:00",
      "author": "CBC News",
      "content_type": "rss news summary",
      "image_url": "",
      "thai_demo": "",
      "provider_key": "rss_cbc-news-canada"
    },
    {
      "id": "e6bd38163717cb5ccf",
      "provider": "CBC News",
      "title": "Toronto saw significant increase in speeders after camera removals: city report",
      "description": "In a new report Mayor Olivia Chow describes as \"horrifying,\" Toronto transportation staff say there has been a significant increase in speeding where cameras used to be located in the city.",
      "url": "https://www.cbc.ca/news/canada/toronto/toronto-speeding-after-speed-camera-removal-9.7246983?cmp=rss",
      "category": "Canada",
      "published": "2026-06-24T13:59:10+00:00",
      "author": "CBC News",
      "content_type": "rss news summary",
      "image_url": "",
      "thai_demo": "",
      "provider_key": "rss_cbc-news-canada"
    },
    {
      "id": "a99794c03b51f12929",
      "provider": "CBC News",
      "title": "La Ronge, Sask., sees record number of high school graduates",
      "description": "The principals of La Ronge's two high school say a block system, a success coach, a caring environment and extra help with assignment are some of the factors that led to an increase in students graduating Grade 12 this year.",
      "url": "https://www.cbc.ca/news/canada/saskatchewan/high-number-of-graduates-in-la-ronge-9.7246178?cmp=rss",
      "category": "Canada",
      "published": "2026-06-24T15:50:46+00:00",
      "author": "CBC News",
      "content_type": "rss news summary",
      "image_url": "",
      "thai_demo": "",
      "provider_key": "rss_cbc-news-canada"
    },
    {
      "id": "d9ffe3cfe4d1031f28",
      "provider": "CBC News",
      "title": "You asked, we answer: Canada's new social media rules for kids",
      "description": "The federal government is moving to restrict social media access for Canadians under the age of 16. Parents, educators and experts have differing opinions on the Safe Social Media Act — and plenty of questions about the details. So you asked, and we answered.",
      "url": "https://www.cbc.ca/player/play/9.7247656?cmp=rss",
      "category": "Canada",
      "published": "2026-06-24T21:08:07+00:00",
      "author": "CBC News",
      "content_type": "rss news summary",
      "image_url": "",
      "thai_demo": "",
      "provider_key": "rss_cbc-news-canada"
    },
    {
      "id": "39848e992269268c0d",
      "provider": "CBC News",
      "title": "Meet the Calgarian behind Team Canada's World Cup 2026 jerseys",
      "description": "Team Canada's 2026 kit has been in the works since the last World Cup four years ago — and it's the brain child of a Calgarian. As the lead designer at Nike for the national team's latest kit, Calgary-based Holly Gallacher was behind the designs of the national team's home and away jerseys.",
      "url": "https://www.cbc.ca/news/canada/calgary/team-canada-soccer-football-2026-kit-9.7246637?cmp=rss",
      "category": "Canada",
      "published": "2026-06-24T19:14:00+00:00",
      "author": "CBC News",
      "content_type": "rss news summary",
      "image_url": "",
      "thai_demo": "",
      "provider_key": "rss_cbc-news-canada"
    },
    {
      "id": "b6abfb4f81550ff6d2",
      "provider": "CBC News",
      "title": "The B.C. heat dome had a deadly impact on New Westminster. 5 years later, cooling is top of mind",
      "description": "Five years after extreme heat killed 33 people in New Westminster, the city has built out a network of cooling stations and passed bylaws aimed at cooling apartments.",
      "url": "https://www.cbc.ca/news/canada/british-columbia/new-west-heat-dome-cooling-9.7246202?cmp=rss",
      "category": "Canada",
      "published": "2026-06-24T12:00:00+00:00",
      "author": "CBC News",
      "content_type": "rss news summary",
      "image_url": "",
      "thai_demo": "",
      "provider_key": "rss_cbc-news-canada"
    },
    {
      "id": "d7fb908970a94203f3",
      "provider": "CBC News",
      "title": "Toronto gang war led police to a trove of evidence in Ryan Wedding cocaine case, court docs say",
      "description": "More than two years after the arrest of alleged hitman Malik Damion Cunningham in a Toronto suburb, new details about the circumstances of the police operation have emerged from unsealed warrant documents. Cunningham was purportedly hired, armed and trained by Ryan Wedding’s alleged drug ring.",
      "url": "https://www.cbc.ca/news/canada/toronto/malik-cunningham-search-warrant-documents-9.7247410?cmp=rss",
      "category": "Canada",
      "published": "2026-06-24T18:15:52+00:00",
      "author": "CBC News",
      "content_type": "rss news summary",
      "image_url": "",
      "thai_demo": "",
      "provider_key": "rss_cbc-news-canada"
    },
    {
      "id": "5822410969a942b515",
      "provider": "CBC News",
      "title": "Carney announcing decision on future of 24 Sussex in coming weeks: sources",
      "description": "Prime minister Mark Carney is expected in the coming weeks to announce the government's decision about the future of 24 Sussex Drive, sources tell CBC News.",
      "url": "https://www.cbc.ca/news/politics/decision-coming-24-sussex-drive-9.7247224?cmp=rss",
      "category": "Canada",
      "published": "2026-06-24T18:24:18+00:00",
      "author": "CBC News",
      "content_type": "rss news summary",
      "image_url": "",
      "thai_demo": "",
      "provider_key": "rss_cbc-news-canada"
    },
    {
      "id": "14163ba093a0848702",
      "provider": "CBC News",
      "title": "Bright fireball in Sault Ste. Marie, Ont., skies 'shocked and amazed' onlookers",
      "description": "Planetary scientists with Western University in London, Ont., say dozens of meteorites from a Friday evening fireball landed on Cockburn Island, a mostly uninhabited land mass in Lake Huron.",
      "url": "https://www.cbc.ca/news/canada/sudbury/fireball-meteor-sault-9.7246298?cmp=rss",
      "category": "Canada",
      "published": "2026-06-23T21:01:06+00:00",
      "author": "CBC News",
      "content_type": "rss news summary",
      "image_url": "",
      "thai_demo": "",
      "provider_key": "rss_cbc-news-canada"
    },
    {
      "id": "b86629e9938d04a135",
      "provider": "CBC News",
      "title": "Why a 25% discount on airfare cost a Montreal couple more — thanks to dynamic pricing",
      "description": "A Montreal couple was confused and upset after they rebooked their Air Canada flight to take advantage of a new sale, and the rebooked tickets cost slightly more. Dynamic pricing, which can cause base fares to fluctuate, was partly to blame. Some experts are calling for more transparency when companies use dynamic pricing during a discount promotion.",
      "url": "https://www.cbc.ca/news/business/dynamic-pricing-sale-fare-air-canada-9.7246024?cmp=rss",
      "category": "Canada",
      "published": "2026-06-24T08:00:00+00:00",
      "author": "CBC News",
      "content_type": "rss news summary",
      "image_url": "",
      "thai_demo": "",
      "provider_key": "rss_cbc-news-canada"
    },
    {
      "id": "f92d05dfd882f59501",
      "provider": "CBC News",
      "title": "N.L. Crown prosecutor charged with smuggling, prohibited weapon possession",
      "description": "The RCMP in eastern Newfoundland have charged a provincial Crown attorney with more than 10 charges related to smuggling, illegal importation, and weapons offences.",
      "url": "https://www.cbc.ca/news/canada/newfoundland-labrador/nl-crown-prosecutor-charged-smuggling-prohibited-weapon-9.7247305?cmp=rss",
      "category": "Canada",
      "published": "2026-06-24T17:45:41+00:00",
      "author": "CBC News",
      "content_type": "rss news summary",
      "image_url": "",
      "thai_demo": "",
      "provider_key": "rss_cbc-news-canada"
    },
    {
      "id": "596acbf128832b00fa",
      "provider": "CBC News",
      "title": "Hamilton city council approves pause on data centre development",
      "description": "City of Hamilton staff will report back to councillors at their next meeting on July 15 with a bylaw imposing a moratorium on the construction of the facilities that securely store, process and distribute digital information.",
      "url": "https://www.cbc.ca/news/canada/hamilton/data-centre-moratorium-9.7247233?cmp=rss",
      "category": "Canada",
      "published": "2026-06-24T16:20:55+00:00",
      "author": "CBC News",
      "content_type": "rss news summary",
      "image_url": "",
      "thai_demo": "",
      "provider_key": "rss_cbc-news-canada"
    },
    {
      "id": "4ce2e78a57136fe53a",
      "provider": "CBC News",
      "title": "Feds push to have 3 northern projects fast-tracked under Building Canada Act",
      "description": "The Liberal government wants a Northwest Territories highway, an Arctic deepwater port and a nuclear waste storage facility in northwestern Ontario to be listed as projects of national interest.",
      "url": "https://www.cbc.ca/news/politics/mpo-greys-bay-mackenzie-highway-nuclear-waste-9.7247003?cmp=rss",
      "category": "Canada",
      "published": "2026-06-24T14:21:10+00:00",
      "author": "CBC News",
      "content_type": "rss news summary",
      "image_url": "",
      "thai_demo": "",
      "provider_key": "rss_cbc-news-canada"
    },
    {
      "id": "e44a093d6ec1833a22",
      "provider": "CBC News",
      "title": "PQ maps out its vision for an independent Quebec in Blue Book on sovereignty",
      "description": "Quebec independence would yield $13 billion to $16 billion in administrative savings by eliminating or merging most of the roughly 230 federal agencies operating in the province, Parti Québécois (PQ) Leader Paul St-Pierre Plamondon announced Tuesday.",
      "url": "https://www.cbc.ca/news/canada/montreal/pq-blue-book-9.7247277?cmp=rss",
      "category": "Canada",
      "published": "2026-06-24T16:39:03+00:00",
      "author": "CBC News",
      "content_type": "rss news summary",
      "image_url": "",
      "thai_demo": "",
      "provider_key": "rss_cbc-news-canada"
    },
    {
      "id": "95fb0494a7121866d1",
      "provider": "CBC News",
      "title": "Abuse alleged at N.L. preschool as parents demand answers",
      "description": "Parents of children who attended a pre-kindergarten program in eastern Newfoundland say their kids were knelt on, yelled at, and locked in a bathroom by an early childhood educator who police investigated but never charged.",
      "url": "https://www.cbc.ca/news/canada/newfoundland-labrador/abuse-alleged-at-n-l-preschool-as-parents-demand-answers-9.7238779?cmp=rss",
      "category": "Canada",
      "published": "2026-06-24T08:30:00+00:00",
      "author": "CBC News",
      "content_type": "rss news summary",
      "image_url": "",
      "thai_demo": "",
      "provider_key": "rss_cbc-news-canada"
    },
    {
      "id": "d439297b91bf9885cd",
      "provider": "CBC News",
      "title": "Aurora, Ont., to remove Frank Stronach's name from recreation complex after sexual assault conviction",
      "description": "The Town of Aurora will remove Frank Stronach's name from its Aurora Recreation Complex after the 93-year-old Canadian billionaire was found guilty of one count of sexual assault and one count of indecent assault at his trial last week.",
      "url": "https://www.cbc.ca/news/canada/toronto/aurora-recreation-complex-frank-stronach-9.7247355?cmp=rss",
      "category": "Canada",
      "published": "2026-06-24T16:56:05+00:00",
      "author": "CBC News",
      "content_type": "rss news summary",
      "image_url": "",
      "thai_demo": "",
      "provider_key": "rss_cbc-news-canada"
    },
    {
      "id": "48d9defd5bc1fe0d7d",
      "provider": "CBC News",
      "title": "Orillia, Ont., to decide fate of controversial Samuel de Champlain statue",
      "description": "As the central Ontario city of Orillia decides what will happen to an imposing, century-old statue of Samuel de Champlain, it remains hidden away in storage. The city council will choose to either restore it, modify it, send it away or melt it down.",
      "url": "https://www.cbc.ca/news/politics/orillia-champlain-statue-taken-down-9.7246284?cmp=rss",
      "category": "Canada",
      "published": "2026-06-24T08:00:00+00:00",
      "author": "CBC News",
      "content_type": "rss news summary",
      "image_url": "",
      "thai_demo": "",
      "provider_key": "rss_cbc-news-canada"
    },
    {
      "id": "b79ca61727633128ab",
      "provider": "CBC News",
      "title": "Does it seem easier to book a dermatologist for Botox than a mole check? You're not alone",
      "description": "Across the country, Canadians are waiting months to get access to a dermatologist for medical purposes, including skin checks, mole removals, eczema and psoriasis.",
      "url": "https://www.cbc.ca/news/health/canada-dermatologists-medical-purposes-9.7246368?cmp=rss",
      "category": "Canada",
      "published": "2026-06-24T08:00:00+00:00",
      "author": "CBC News",
      "content_type": "rss news summary",
      "image_url": "",
      "thai_demo": "",
      "provider_key": "rss_cbc-news-canada"
    },
    {
      "id": "797c1a155e0ac1dbef",
      "provider": "CBC News",
      "title": "Trump's D.C. reflecting pool is the butt of online jokes. What happened?",
      "description": "The pool's $14.7-million US renovation and subsequent rapid deterioration has become the butt of internet jokes. Some have dubbed June \"ALGAEBTQ Pride Month\" or commented that Trump, who promised to \"drain the swamp\" in Washington, has instead created a swamp.",
      "url": "https://www.cbc.ca/news/world/trump-reflecting-pool-renovations-9.7248005?cmp=rss",
      "category": "World",
      "published": "2026-06-24T23:36:25+00:00",
      "author": "CBC News",
      "content_type": "rss news summary",
      "image_url": "",
      "thai_demo": "",
      "provider_key": "rss_cbc-news-world"
    },
    {
      "id": "00f7e73e58091abbb6",
      "provider": "CBC News",
      "title": "Strong back-to-back earthquakes hit Venezuela prompting fears of heavy casualities",
      "description": "Two strong earthquakes shook north-central Venezuela on Wednesday afternoon, collapsing buildings in the capital Caracas and prompting scientists to warn of potentially heavy casualties and ‌widespread destruction across the South American country.",
      "url": "https://www.cbc.ca/news/world/earthquake-venezuela-caracas-9.7248076?cmp=rss",
      "category": "World",
      "published": "2026-06-24T23:53:45+00:00",
      "author": "CBC News",
      "content_type": "rss news summary",
      "image_url": "",
      "thai_demo": "",
      "provider_key": "rss_cbc-news-world"
    },
    {
      "id": "e5bd58bf2fb002f26f",
      "provider": "CBC News",
      "title": "What we learned from Bill Gates's interview with Congress about Epstein",
      "description": "Microsoft founder and philanthropist Bill Gates told a congressional panel that files released by the Justice Department in January only added to his embarrassment over interacting with the late sex offender Jeffrey Epstein.",
      "url": "https://www.cbc.ca/news/world/house-committee-epstein-gates-transcript-9.7246870?cmp=rss",
      "category": "World",
      "published": "2026-06-24T16:12:59+00:00",
      "author": "CBC News",
      "content_type": "rss news summary",
      "image_url": "",
      "thai_demo": "",
      "provider_key": "rss_cbc-news-world"
    },
    {
      "id": "9c2680069865cca0fe",
      "provider": "CBC News",
      "title": "Trump threatened new tolls in the Strait of Hormuz. What if other countries follow suit?",
      "description": "U.S. President Donald Trump threatened to impose new tolls in the Strait of Hormuz last weekend, sparking worries that the practice of charging to pass through critical waterways could spread — with devastating consequences to the global economy. Iran has blocked the strait for much of the war, reportedly charging tolls as high as $2 million US for ships it allows to pass.",
      "url": "https://www.cbc.ca/news/world/trump-iran-strait-of-hormuz-tolls-9.7246282?cmp=rss",
      "category": "World",
      "published": "2026-06-24T08:00:00+00:00",
      "author": "CBC News",
      "content_type": "rss news summary",
      "image_url": "",
      "thai_demo": "",
      "provider_key": "rss_cbc-news-world"
    },
    {
      "id": "463cbc8a2bd8c06a96",
      "provider": "CBC News",
      "title": "'No need for panic' on Ebola case in France, WHO chief says",
      "description": "WHO director general Tedros Adhanom Ghebreyesus, speaking on Wednesday about the ongoing Ebola outbreak in the Democratic Republic of Congo and Uganda, weighed in on the report of a recent case of Ebola in a doctor in France who had worked in Congo, saying the risk to the rest of the world remains low.",
      "url": "https://www.cbc.ca/player/play/9.7247362?cmp=rss",
      "category": "World",
      "published": "2026-06-24T16:58:22+00:00",
      "author": "CBC News",
      "content_type": "rss news summary",
      "image_url": "",
      "thai_demo": "",
      "provider_key": "rss_cbc-news-world"
    },
    {
      "id": "0041bfa94407e71186",
      "provider": "CBC News",
      "title": "India’s Cockroach Party shows frustrated Gen-Zers are hard to crush",
      "description": "India’s Cockroach Janta Party has extended its protest in Delhi to a fourth day, as it demands the resignation of the country's education minister. The CJP, which emerged just over a month ago, is aimed at India’s bulging youth demographic, which is frustrated over a lack of jobs and a test scandal in education.",
      "url": "https://www.cbc.ca/news/world/india-cockroach-party-gen-z-jobs-students-9.7245593?cmp=rss",
      "category": "World",
      "published": "2026-06-24T08:00:00+00:00",
      "author": "CBC News",
      "content_type": "rss news summary",
      "image_url": "",
      "thai_demo": "",
      "provider_key": "rss_cbc-news-world"
    },
    {
      "id": "2486340a5bbab3d155",
      "provider": "CBC News",
      "title": "Bosnia-Herzegovina boosts chances of advancing at World Cup with win over Qatar",
      "description": "Bosnia-Herzegovina eliminated Qatar and increased its chances of advancing at the World Cup with a 3-1 victory in a Group B match on Wednesday in Seattle.",
      "url": "https://www.cbc.ca/sports/soccer/worldcup/fifa-world-cup-qatar-bosnia-herzegovina-recap-june-24-9.7246839?cmp=rss",
      "category": "World",
      "published": "2026-06-24T21:20:47+00:00",
      "author": "CBC News",
      "content_type": "rss news summary",
      "image_url": "",
      "thai_demo": "",
      "provider_key": "rss_cbc-news-world"
    },
    {
      "id": "9e0a5997d60cc20835",
      "provider": "CBC News",
      "title": "While focus remains on men's World Cup, clock starts on 2027 Women's World Cup",
      "description": "While most of the soccer world is focused on the men at the World Cup, the countdown has begun for the 2027 Women's World Cup in Brazil.",
      "url": "https://www.cbc.ca/sports/soccer/worldcup/world-cup-fifa-women-men-9.7247749?cmp=rss",
      "category": "World",
      "published": "2026-06-24T20:21:38+00:00",
      "author": "CBC News",
      "content_type": "rss news summary",
      "image_url": "",
      "thai_demo": "",
      "provider_key": "rss_cbc-news-world"
    },
    {
      "id": "2ba08dd9b9b9c144eb",
      "provider": "CBC News",
      "title": "Ukraine launches drone offensive in Crimea and inside Russia, where fuel shortages are taking a toll",
      "description": "Ukrainian drones knocked out power in the biggest city in Russian-held Crimea on Wednesday and targeted facilities ‌in central and southern Russia, underscoring the reach of Kyiv's attacks on energy infrastructure.",
      "url": "https://www.cbc.ca/news/world/russia-ukraine-war-1582-crimea-drones-9.7246857?cmp=rss",
      "category": "World",
      "published": "2026-06-24T10:54:04+00:00",
      "author": "CBC News",
      "content_type": "rss news summary",
      "image_url": "",
      "thai_demo": "",
      "provider_key": "rss_cbc-news-world"
    },
    {
      "id": "c4e243e9e7da467329",
      "provider": "CBC News",
      "title": "Deadly 'Omega' heat wave breaks more temperature records in Europe",
      "description": "Western Europe was in the grip of a heat wave on Wednesday that claimed dozens of lives, disrupted power supplies, shut schools and cultural landmarks, as forecasters warned the extreme temperatures could persist until the end of the week.",
      "url": "https://www.cbc.ca/news/world/extreme-heat-wave-europe-omega-9.7246908?cmp=rss",
      "category": "World",
      "published": "2026-06-24T12:22:41+00:00",
      "author": "CBC News",
      "content_type": "rss news summary",
      "image_url": "",
      "thai_demo": "",
      "provider_key": "rss_cbc-news-world"
    },
    {
      "id": "5edd8214d4dfe48f60",
      "provider": "CBC News",
      "title": "As major U.S. Supreme Court decisions loom, how far will it let Trump go?",
      "description": "America’s top court is set to deliver decisions on more than a dozen major cases in the coming days. And with rulings on birthright citizenship, transgender athletes and the Federal Reserve on the docket, there’s a lot at stake as the U.S. president’s agenda is tested by the justice system.",
      "url": "https://www.cbc.ca/news/politics/donald-trump-supreme-court-9.7246967?cmp=rss",
      "category": "World",
      "published": "2026-06-24T14:49:27+00:00",
      "author": "CBC News",
      "content_type": "rss news summary",
      "image_url": "",
      "thai_demo": "",
      "provider_key": "rss_cbc-news-world"
    },
    {
      "id": "d96a7f3146f70b3f37",
      "provider": "CBC News",
      "title": "Woman killed in Israeli strike in Lebanon remembered as defender of endangered sea turtles",
      "description": "Mona Khalil, who turned her beachfront home in southern Lebanon into a conservation hub for endangered sea turtles, succumbed to her wounds from an Israeli strike on her home.",
      "url": "https://www.cbc.ca/radio/asithappens/mona-khalil-obit-9.7246301?cmp=rss",
      "category": "World",
      "published": "2026-06-24T14:54:41+00:00",
      "author": "CBC News",
      "content_type": "rss news summary",
      "image_url": "",
      "thai_demo": "",
      "provider_key": "rss_cbc-news-world"
    },
    {
      "id": "eeb0897d3443dfd9e3",
      "provider": "CBC News",
      "title": "Michigan Senate candidate accuses Trump of keeping Canada-U.S. bridge closed to help donor",
      "description": "Mallory McMorrow's new ad accuses Trump of blocking the opening of the Gordie Howe International Bridge and suggests he is doing it to benefit a major political donor, building on an anti-corruption message she has sought to make central to her campaign.",
      "url": "https://www.cbc.ca/news/canada/windsor/michigan-senate-candidate-accuses-trump-of-keeping-canada-us-bridge-closed-to-help-donor-9.7246991?cmp=rss",
      "category": "World",
      "published": "2026-06-24T13:59:31+00:00",
      "author": "CBC News",
      "content_type": "rss news summary",
      "image_url": "",
      "thai_demo": "",
      "provider_key": "rss_cbc-news-world"
    },
    {
      "id": "b74f11d743958500e6",
      "provider": "CBC News",
      "title": "Landmark legal win compensates pregnant soccer player who lost contract",
      "description": "In a landmark legal win for female soccer players, sport's highest court has awarded Maja Göthberg salary compensation from Lazio Women after the Italian club ended contract talks when it knew she was pregnant.",
      "url": "https://www.cbc.ca/sports/olympics/summer/court-arbitration-sport-landmark-pregnancy-ruling-june-24-9.7246963?cmp=rss",
      "category": "World",
      "published": "2026-06-24T13:43:23+00:00",
      "author": "CBC News",
      "content_type": "rss news summary",
      "image_url": "",
      "thai_demo": "",
      "provider_key": "rss_cbc-news-world"
    },
    {
      "id": "cd99a332531bd4fe79",
      "provider": "CBC News",
      "title": "Love Story or Hoax? All of the Taylor Swift-Travis Kelce wedding rumours",
      "description": "It’s a date likely etched into the minds of many Swifties: Aug. 26, 2025 — the day Taylor Swift and Travis Kelce announced their engagement on Instagram. Since then, fans have been fixated on uncovering possible details about when and where the wedding may take place.",
      "url": "https://www.cbc.ca/news/entertainment/taylor-swift-travis-kelce-wedding-rumours-2026-9.7246294?cmp=rss",
      "category": "World",
      "published": "2026-06-24T12:19:41+00:00",
      "author": "CBC News",
      "content_type": "rss news summary",
      "image_url": "",
      "thai_demo": "",
      "provider_key": "rss_cbc-news-world"
    },
    {
      "id": "982d1ec75b05d29976",
      "provider": "CBC News",
      "title": "Israel committed genocide in Gaza, deliberately targeted Palestinian children: UN report",
      "description": "The UN's Commission of Inquiry found that Israel had genocidal intent in the Gaza Strip during the war, with the key indicator being its targeting of children. The Gaza Health ministry says that since the ceasefire began in October 2025, more than 1,000 people died, 265 of them children.",
      "url": "https://www.cbc.ca/news/world/un-report-gaza-children-genocide-9.7246490?cmp=rss",
      "category": "World",
      "published": "2026-06-24T01:34:28+00:00",
      "author": "CBC News",
      "content_type": "rss news summary",
      "image_url": "",
      "thai_demo": "",
      "provider_key": "rss_cbc-news-world"
    },
    {
      "id": "7016dd7ac781a3ffba",
      "provider": "CBC News",
      "title": "Brexit, 10 years later: What a regret-fuelled British town can teach Canada about referendums",
      "description": "A decade after Britain voted to leave Europe, neither side is happy, offering a cautionary tale for Canadians about the risks of referendums.",
      "url": "https://www.cbc.ca/news/world/10-years-after-brexit-9.7245611?cmp=rss",
      "category": "World",
      "published": "2026-06-23T20:06:20+00:00",
      "author": "CBC News",
      "content_type": "rss news summary",
      "image_url": "",
      "thai_demo": "",
      "provider_key": "rss_cbc-news-world"
    },
    {
      "id": "11e7e8bf05c5d74bab",
      "provider": "CBC News",
      "title": "Five Eyes cybersecurity agencies warn of new AI models impact on cyber risks",
      "description": "Cutting-edge artificial intelligence technology is poised to supercharge offensive hacking capabilities, and urgent action is needed to face up to the ‌threat, U.S., British, Canadian, Australian and New Zealand cybersecurity agency officials said on Monday.",
      "url": "https://www.cbc.ca/news/canada/five-eyes-ai-cyber-risk-warning-9.7245294?cmp=rss",
      "category": "World",
      "published": "2026-06-23T20:20:47+00:00",
      "author": "CBC News",
      "content_type": "rss news summary",
      "image_url": "",
      "thai_demo": "",
      "provider_key": "rss_cbc-news-world"
    },
    {
      "id": "22dfbb08d70192d740",
      "provider": "CBC News",
      "title": "Do you want AI with that? Chatbots could take your next order at the drive-thru",
      "description": "Across the United States, fast food chains are turning to AI to run their drive-thru counters - and Canada could be next. Companies say the technology now has higher accuracy than human employees - and some labour organizers worry it could displace fast food workers.",
      "url": "https://www.cbc.ca/news/business/ai-chatbot-drive-thru-9.7245215?cmp=rss",
      "category": "Business",
      "published": "2026-06-23T08:00:00+00:00",
      "author": "CBC News",
      "content_type": "rss news summary",
      "image_url": "",
      "thai_demo": "",
      "provider_key": "rss_cbc-news-business"
    },
    {
      "id": "80373cc7a53a2ef634",
      "provider": "CBC News",
      "title": "Tesla being investigated after car drives into home, killing 76-year-old woman",
      "description": "The top U.S. auto regulator opened an investigation Monday after a Tesla using an automated driving feature slammed into a Texas home at high speed and killed a 76-year-old woman standing inside.",
      "url": "https://www.cbc.ca/news/world/tesla-investigation-crash-texas-home-9.7246137?cmp=rss",
      "category": "Business",
      "published": "2026-06-23T20:47:25+00:00",
      "author": "CBC News",
      "content_type": "rss news summary",
      "image_url": "",
      "thai_demo": "",
      "provider_key": "rss_cbc-news-business"
    },
    {
      "id": "f85c322b1ee05fb3d6",
      "provider": "CBC News",
      "title": "Tech stocks drop, pulling world shares down",
      "description": "Stocks slumped on Wall Street on Tuesday as a sell-off in big technology stocks spread from Asia back to the U.S. over worries about potentially higher interest rates by the end of the year.",
      "url": "https://www.cbc.ca/news/business/stock-markets-june-23-9.7245513?cmp=rss",
      "category": "Business",
      "published": "2026-06-23T13:28:09+00:00",
      "author": "CBC News",
      "content_type": "rss news summary",
      "image_url": "",
      "thai_demo": "",
      "provider_key": "rss_cbc-news-business"
    },
    {
      "id": "fc3a09f2a1501d99c6",
      "provider": "BBC News",
      "title": "France, UK and Spain see record temperatures as heatwave grips western Europe",
      "description": "Tens of millions of people are grappling with punishing temperatures, which have led to red heat alerts across the continent.",
      "url": "https://www.bbc.co.uk/news/articles/c78y4102n1zo?at_medium=RSS&at_campaign=rss",
      "category": "World",
      "published": "2026-06-24T21:39:18+00:00",
      "author": "BBC News",
      "content_type": "rss news summary",
      "image_url": "https://ichef.bbci.co.uk/ace/standard/240/cpsprodpb/1e66/live/9b1b95b0-6feb-11f1-a9c4-37da5d161ee0.jpg",
      "thai_demo": "",
      "provider_key": "rss_bbc-news-world"
    },
    {
      "id": "a15befb9736ddd5697",
      "provider": "BBC News",
      "title": "UN nuclear chief says inspectors will visit Iran sites as part of war deal",
      "description": "Rafael Grossi says the IAEA is \"working on modalities\" but an Iranian minister says such access would only be part of a final deal with the US.",
      "url": "https://www.bbc.co.uk/news/articles/cpd395zv81vo?at_medium=RSS&at_campaign=rss",
      "category": "World",
      "published": "2026-06-24T17:31:48+00:00",
      "author": "BBC News",
      "content_type": "rss news summary",
      "image_url": "https://ichef.bbci.co.uk/ace/standard/240/cpsprodpb/fcc8/live/65f531e0-6ff3-11f1-8e1d-bbbb1017d210.jpg",
      "thai_demo": "",
      "provider_key": "rss_bbc-news-world"
    },
    {
      "id": "5f760ee0c3ff0468de",
      "provider": "BBC News",
      "title": "Clean sweep for Mamdani-backed candidates in New York's Democratic primary",
      "description": "Brad Lander unseats Dan Goldman in a race that laid bare the city's divisions over the Israel-Gaza war.",
      "url": "https://www.bbc.co.uk/news/articles/clye652m41po?at_medium=RSS&at_campaign=rss",
      "category": "World",
      "published": "2026-06-24T13:03:35+00:00",
      "author": "BBC News",
      "content_type": "rss news summary",
      "image_url": "https://ichef.bbci.co.uk/ace/standard/240/cpsprodpb/bde8/live/87a1ba60-6f86-11f1-8546-8f19e4fe30f4.jpg",
      "thai_demo": "",
      "provider_key": "rss_bbc-news-world"
    },
    {
      "id": "ad012cfbb4cd8f4605",
      "provider": "BBC News",
      "title": "France confirms first Ebola case",
      "description": "The French doctor had been working in DR Congo, where more than 260 people are known to have died.",
      "url": "https://www.bbc.co.uk/news/articles/cj9gzr9rdjlo?at_medium=RSS&at_campaign=rss",
      "category": "World",
      "published": "2026-06-24T15:00:52+00:00",
      "author": "BBC News",
      "content_type": "rss news summary",
      "image_url": "https://ichef.bbci.co.uk/ace/standard/240/cpsprodpb/c26d/live/6fcbfc90-6fb1-11f1-b1db-af71d47507d6.jpg",
      "thai_demo": "",
      "provider_key": "rss_bbc-news-world"
    },
    {
      "id": "19a22f4d609ebc284b",
      "provider": "BBC News",
      "title": "French woman allegedly held captive by husband for 12 years rescued in Pakistan",
      "description": "Yasmina alleges she was held along with her five children, and they were all cut off from the outside world.",
      "url": "https://www.bbc.co.uk/news/articles/cj0g71pnv3no?at_medium=RSS&at_campaign=rss",
      "category": "World",
      "published": "2026-06-24T08:29:06+00:00",
      "author": "BBC News",
      "content_type": "rss news summary",
      "image_url": "https://ichef.bbci.co.uk/ace/standard/240/cpsprodpb/cea0/live/b3378670-6fcf-11f1-8546-8f19e4fe30f4.jpg",
      "thai_demo": "",
      "provider_key": "rss_bbc-news-world"
    },
    {
      "id": "aa8c3e38fe81042e33",
      "provider": "BBC News",
      "title": "Colombia's left-wing presidential candidate concedes defeat",
      "description": "Senator Iván Cepeda was beaten by right-wing businessman Abelardo de la Espriella by less than a percentage point.",
      "url": "https://www.bbc.co.uk/news/articles/cgrkqky5lzpo?at_medium=RSS&at_campaign=rss",
      "category": "World",
      "published": "2026-06-24T15:50:22+00:00",
      "author": "BBC News",
      "content_type": "rss news summary",
      "image_url": "https://ichef.bbci.co.uk/ace/standard/240/cpsprodpb/32ca/live/7c140e90-6fe1-11f1-b763-7be8e457290d.jpg",
      "thai_demo": "",
      "provider_key": "rss_bbc-news-world"
    },
    {
      "id": "b8716ba75ad5857a25",
      "provider": "BBC News",
      "title": "Sydney woman wakes from induced coma more than a week after shark attack",
      "description": "Leah Stewart, 34, had one of her arms amputated after she was bitten while swimming at Coogee Beach.",
      "url": "https://www.bbc.co.uk/news/articles/cy8drk2dk3no?at_medium=RSS&at_campaign=rss",
      "category": "World",
      "published": "2026-06-24T01:42:43+00:00",
      "author": "BBC News",
      "content_type": "rss news summary",
      "image_url": "https://ichef.bbci.co.uk/ace/standard/240/cpsprodpb/2cf2/live/1cb13550-6f6d-11f1-a190-1943df672931.jpg",
      "thai_demo": "",
      "provider_key": "rss_bbc-news-world"
    },
    {
      "id": "2c33f37ad4433ad218",
      "provider": "BBC News",
      "title": "Bondi Beach shooting hero pleads not guilty to alleged assault on his father",
      "description": "Ahmed al Ahmed tackled one of the gunmen who killed 15 people at a Jewish event in December.",
      "url": "https://www.bbc.co.uk/news/articles/cn8q33gdgjjo?at_medium=RSS&at_campaign=rss",
      "category": "World",
      "published": "2026-06-24T04:06:51+00:00",
      "author": "BBC News",
      "content_type": "rss news summary",
      "image_url": "https://ichef.bbci.co.uk/ace/standard/240/cpsprodpb/9ce3/live/0c6d0f60-5ffb-11f1-a129-231866914bc9.jpg",
      "thai_demo": "",
      "provider_key": "rss_bbc-news-world"
    },
    {
      "id": "939ee15bee9898ee13",
      "provider": "BBC News",
      "title": "Kenya to charge students with murder over deadly school fire",
      "description": "Sixteen pupils, aged between 15 and 18, died when a fire broke out in a dormitory at Utumishi Girls' School last month.",
      "url": "https://www.bbc.co.uk/news/articles/cwykl517xk7o?at_medium=RSS&at_campaign=rss",
      "category": "World",
      "published": "2026-06-24T14:36:42+00:00",
      "author": "BBC News",
      "content_type": "rss news summary",
      "image_url": "https://ichef.bbci.co.uk/ace/standard/240/cpsprodpb/9fe5/live/7abd54a0-6f93-11f1-acc7-d7e31563f96c.jpg",
      "thai_demo": "",
      "provider_key": "rss_bbc-news-world"
    },
    {
      "id": "f19f013ef044906d72",
      "provider": "BBC News",
      "title": "Congress passes war powers measure for first time, breaking with Trump over Iran",
      "description": "Experts say Trump is likely to ignore it, but that even though it carries little power, it is politically significant.",
      "url": "https://www.bbc.co.uk/news/articles/ce8j6g3v3r4o?at_medium=RSS&at_campaign=rss",
      "category": "World",
      "published": "2026-06-24T14:57:21+00:00",
      "author": "BBC News",
      "content_type": "rss news summary",
      "image_url": "https://ichef.bbci.co.uk/ace/standard/240/cpsprodpb/340e/live/f69c8770-6f7b-11f1-8e1d-bbbb1017d210.jpg",
      "thai_demo": "",
      "provider_key": "rss_bbc-news-world"
    },
    {
      "id": "8aeb9f1738e543ca5f",
      "provider": "BBC News",
      "title": "Dozens of ships head through Strait of Hormuz after US-Iran deal",
      "description": "Traffic in the waterway has risen since the US and Iran signed a deal aimed at ending the war, including 42 ships on Saturday alone.",
      "url": "https://www.bbc.co.uk/news/articles/cx23rnzdgl8o?at_medium=RSS&at_campaign=rss",
      "category": "World",
      "published": "2026-06-23T14:55:31+00:00",
      "author": "BBC News",
      "content_type": "rss news summary",
      "image_url": "https://ichef.bbci.co.uk/ace/standard/240/cpsprodpb/bd09/live/958bc530-6f09-11f1-8546-8f19e4fe30f4.png",
      "thai_demo": "",
      "provider_key": "rss_bbc-news-world"
    },
    {
      "id": "456a368ef02bdce415",
      "provider": "BBC News",
      "title": "Chinese e-commerce giant Alibaba sues US government over defence blacklist",
      "description": "It is suing the US defence department after it was added to a list of firms with ties to the Chinese military.",
      "url": "https://www.bbc.co.uk/news/articles/ckg0258vpvqo?at_medium=RSS&at_campaign=rss",
      "category": "World",
      "published": "2026-06-23T23:25:07+00:00",
      "author": "BBC News",
      "content_type": "rss news summary",
      "image_url": "https://ichef.bbci.co.uk/ace/standard/240/cpsprodpb/1bfe/live/8a2019f0-6f5c-11f1-9ab9-83454fe8fa79.jpg",
      "thai_demo": "",
      "provider_key": "rss_bbc-news-world"
    },
    {
      "id": "bb2ee17c5b7680acae",
      "provider": "BBC News",
      "title": "From startups to global spotlight - Indian entrepreneur takes charge of WhatsApp",
      "description": "Kunal Shah has been a recognisable figure in India's startup ecosystem for a while but now he faces global spotlight.",
      "url": "https://www.bbc.co.uk/news/articles/c0my4n38myjo?at_medium=RSS&at_campaign=rss",
      "category": "World",
      "published": "2026-06-23T21:57:05+00:00",
      "author": "BBC News",
      "content_type": "rss news summary",
      "image_url": "https://ichef.bbci.co.uk/ace/standard/240/cpsprodpb/cdfa/live/981f95a0-6eec-11f1-8546-8f19e4fe30f4.jpg",
      "thai_demo": "",
      "provider_key": "rss_bbc-news-world"
    },
    {
      "id": "fcea36016f59d98553",
      "provider": "BBC News",
      "title": "'We're begging' - Savannah Guthrie pleads for help as details of her mother’s case emerge",
      "description": "Savannah Guthrie spoke on NBC's Today show about a note sent to the media in February regarding her missing mother, Nancy Guthrie, which claimed she had died.",
      "url": "https://www.bbc.co.uk/news/videos/cjdg1enzrk5o?at_medium=RSS&at_campaign=rss",
      "category": "World",
      "published": "2026-06-23T16:41:44+00:00",
      "author": "BBC News",
      "content_type": "rss news summary",
      "image_url": "https://ichef.bbci.co.uk/ace/standard/240/cpsprodpb/241f/live/e060c8d0-6f1d-11f1-b1db-af71d47507d6.jpg",
      "thai_demo": "",
      "provider_key": "rss_bbc-news-world"
    },
    {
      "id": "e28e30b355cf3e57a4",
      "provider": "BBC News",
      "title": "Why was JD Vance in a luxury Swiss resort for talks with Iran?",
      "description": "BBC correspondent Jessica Parker explains some key points of the direct talks between the US vice-president and Iran.",
      "url": "https://www.bbc.co.uk/news/videos/c4gyenl6nz0o?at_medium=RSS&at_campaign=rss",
      "category": "World",
      "published": "2026-06-23T05:38:36+00:00",
      "author": "BBC News",
      "content_type": "rss news summary",
      "image_url": "https://ichef.bbci.co.uk/ace/standard/240/cpsprodpb/c00d/live/2cba3e70-6ec2-11f1-8e1d-bbbb1017d210.jpg",
      "thai_demo": "",
      "provider_key": "rss_bbc-news-world"
    },
    {
      "id": "0313ec80b16996ac03",
      "provider": "BBC News",
      "title": "GTA 6 will cost £70 - and physical edition will not contain a disc",
      "description": "Rockstar has said physical copies of the game will contain a code for a digital download for the game.",
      "url": "https://www.bbc.co.uk/news/articles/cjrg52egw1ro?at_medium=RSS&at_campaign=rss",
      "category": "Technology",
      "published": "2026-06-24T23:20:12+00:00",
      "author": "BBC News",
      "content_type": "rss news summary",
      "image_url": "https://ichef.bbci.co.uk/ace/standard/240/cpsprodpb/8a00/live/c7ebc1c0-6f1c-11f1-a375-a3e02c3e348e.jpg",
      "thai_demo": "",
      "provider_key": "rss_bbc-news-technology"
    },
    {
      "id": "562f46fddfec26e16a",
      "provider": "BBC News",
      "title": "Scientist publishes fresh doubts over Microsoft's quantum claims",
      "description": "The tech giant has consistently stood by its Majorana chip research despite scepticism from some experts in the field.",
      "url": "https://www.bbc.co.uk/news/articles/c05y9pl3ejmo?at_medium=RSS&at_campaign=rss",
      "category": "Technology",
      "published": "2026-06-24T15:00:34+00:00",
      "author": "BBC News",
      "content_type": "rss news summary",
      "image_url": "https://ichef.bbci.co.uk/ace/standard/240/cpsprodpb/823e/live/9bf6bfd0-5e9a-11f1-95ff-f5086c3b3d40.jpg",
      "thai_demo": "",
      "provider_key": "rss_bbc-news-technology"
    },
    {
      "id": "2d075227c3ddd1dff8",
      "provider": "BBC News",
      "title": "Steam Machine launches with £879 price tag as Valve cites component costs",
      "description": "Valve said the cost of its PC-console hybrid reflects a broader trend of component costs rising over time.",
      "url": "https://www.bbc.co.uk/news/articles/c0kyzk2p255o?at_medium=RSS&at_campaign=rss",
      "category": "Technology",
      "published": "2026-06-23T11:25:54+00:00",
      "author": "BBC News",
      "content_type": "rss news summary",
      "image_url": "https://ichef.bbci.co.uk/ace/standard/240/cpsprodpb/3325/live/a5fd3fc0-6ef0-11f1-b3b4-39330bfcd14d.png",
      "thai_demo": "",
      "provider_key": "rss_bbc-news-technology"
    },
    {
      "id": "1df5995cf717bd63bf",
      "provider": "BBC News",
      "title": "Why this heatwave feels worse than the last one",
      "description": "A combination of factors is making this heatwave more uncomfortable than some we have had in the past, as Simon King explains",
      "url": "https://www.bbc.co.uk/weather/articles/c3vyzly206no?at_medium=RSS&at_campaign=rss",
      "category": "Science",
      "published": "2026-06-24T12:24:39+00:00",
      "author": "BBC News",
      "content_type": "rss news summary",
      "image_url": "https://ichef.bbci.co.uk/ace/standard/240/cpsprodpb/5db2/live/91a05a20-6fcd-11f1-8e1d-bbbb1017d210.jpg",
      "thai_demo": "",
      "provider_key": "rss_bbc-news-science"
    },
    {
      "id": "2efbbb81e7e9b0c132",
      "provider": "BBC News",
      "title": "Environmental plan is largely off track, warns watchdog",
      "description": "A report says many of the measures are \"well within the reach\" of government and it was a matter of \"moving away from planning into delivery\".",
      "url": "https://www.bbc.co.uk/news/articles/cqj1e0zqvyxo?at_medium=RSS&at_campaign=rss",
      "category": "Science",
      "published": "2026-06-24T05:24:47+00:00",
      "author": "BBC News",
      "content_type": "rss news summary",
      "image_url": "https://ichef.bbci.co.uk/ace/standard/240/cpsprodpb/9f90/live/fec978e0-6f1c-11f1-a375-a3e02c3e348e.jpg",
      "thai_demo": "",
      "provider_key": "rss_bbc-news-science"
    },
    {
      "id": "f1c6e3b5cb4ec448bf",
      "provider": "BBC News",
      "title": "Hundreds of schools plan closures ahead of red heat alerts",
      "description": "The temperature topped 34.6 C in Wisley, England, on Tuesday while Scotland and Northern Ireland saw their hottest days of the year.",
      "url": "https://www.bbc.co.uk/news/articles/cwyl940y94xo?at_medium=RSS&at_campaign=rss",
      "category": "Science",
      "published": "2026-06-24T02:26:39+00:00",
      "author": "BBC News",
      "content_type": "rss news summary",
      "image_url": "https://ichef.bbci.co.uk/ace/standard/240/cpsprodpb/0ab1/live/43f9a4e0-6f35-11f1-a91d-9509c96f4739.jpg",
      "thai_demo": "",
      "provider_key": "rss_bbc-news-science"
    },
    {
      "id": "c0f72d381f654d80da",
      "provider": "BBC News",
      "title": "The UK's summers are getting hotter - but how prepared are we?",
      "description": "Based on current trends parts of the UK are set to see 40C summers regularly within a couple of decades.",
      "url": "https://www.bbc.co.uk/news/articles/c9d2xl3555xo?at_medium=RSS&at_campaign=rss",
      "category": "Science",
      "published": "2026-06-23T23:46:03+00:00",
      "author": "BBC News",
      "content_type": "rss news summary",
      "image_url": "https://ichef.bbci.co.uk/ace/standard/240/cpsprodpb/c399/live/df2453f0-6f9b-11f1-b1db-af71d47507d6.jpg",
      "thai_demo": "",
      "provider_key": "rss_bbc-news-science"
    },
    {
      "id": "388f3d2d2fefe69ce8",
      "provider": "NPR",
      "title": "2 major earthquakes strike northern Venezuela, near Caracas",
      "description": "A 7.2-magnitude earthquake and a 7.5-magnitude were less than a minute apart, said the U.S. Geological Survey. The second earthquake was the largest to hit the country since 1900.",
      "url": "https://www.npr.org/2026/06/24/nx-s1-5869817/2-major-earthquakes-strike-northern-venezuela-near-caracas",
      "category": "World",
      "published": "2026-06-25T03:11:54+00:00",
      "author": "NPR",
      "content_type": "rss news summary",
      "image_url": "",
      "thai_demo": "",
      "provider_key": "rss_npr-world"
    },
    {
      "id": "286dd33633c6b01477",
      "provider": "NPR",
      "title": "Greetings from sweltering Switzerland",
      "description": "On the waterfront in Lucerne, Switzerland, soccer fans watched jumbo TVs showing a World Cup match played an ocean away. But the air felt more like the tropics.",
      "url": "https://www.npr.org/2026/06/24/nx-s1-5867606/lucerne-switzerland-world-cup-heat",
      "category": "World",
      "published": "2026-06-24T11:55:49+00:00",
      "author": "NPR",
      "content_type": "rss news summary",
      "image_url": "",
      "thai_demo": "",
      "provider_key": "rss_npr-world"
    },
    {
      "id": "ffaa4bfeaa0ed9cd8b",
      "provider": "NPR",
      "title": "U.N. nuclear chief says inspectors will visit Iran, but Iran says only after final deal",
      "description": "The head of the U.N.'s atomic agency said Iran's nuclear enrichment sites would be inspected as part of the interim deal. Iran insists any such visit would only come after a final deal.",
      "url": "https://www.npr.org/2026/06/24/g-s1-129770/iran-nuclear-inspection",
      "category": "World",
      "published": "2026-06-24T11:10:17+00:00",
      "author": "NPR",
      "content_type": "rss news summary",
      "image_url": "",
      "thai_demo": "",
      "provider_key": "rss_npr-world"
    },
    {
      "id": "6baf34d8e7a8460bf2",
      "provider": "NPR",
      "title": "Inside the gold-mining town where the Ebola outbreak likely started",
      "description": "NPR reports from Mongbwalu in the Democratic Republic of Congo. The fight to contain the virus faces obstacles from lack of supplies to residents who doubt that the virus is real.",
      "url": "https://www.npr.org/2026/06/24/nx-s1-5863157/ebola-outbreak-democratic-republic-congo-health-crisis",
      "category": "World",
      "published": "2026-06-24T09:00:00+00:00",
      "author": "NPR",
      "content_type": "rss news summary",
      "image_url": "",
      "thai_demo": "",
      "provider_key": "rss_npr-world"
    },
    {
      "id": "52d479a7c75b8bd257",
      "provider": "NPR",
      "title": "As U.S. government looks to leverage food aid, producers seek other delivery methods",
      "description": "The U.S. is changing the way food aid is distributed to starving children around the world. It is now using aid as a diplomatic tool as nutrition bars pile up in U.S. factories.",
      "url": "https://www.npr.org/2026/06/24/nx-s1-5843163/as-u-s-government-looks-to-leverage-food-aid-producers-seek-other-delivery-methods",
      "category": "World",
      "published": "2026-06-24T08:39:32+00:00",
      "author": "NPR",
      "content_type": "rss news summary",
      "image_url": "",
      "thai_demo": "",
      "provider_key": "rss_npr-world"
    },
    {
      "id": "e680e0e39a8e91a92d",
      "provider": "NPR",
      "title": "Archaeologists find huge Viking textile production site in Denmark",
      "description": "Archaeologists have discovered a huge Viking Age textile production site in Denmark that dates back more than 1,000 years and underlines the sophistication of Viking society.",
      "url": "https://www.npr.org/2026/06/24/g-s1-129750/viking-textile-production-site",
      "category": "World",
      "published": "2026-06-24T05:54:49+00:00",
      "author": "NPR",
      "content_type": "rss news summary",
      "image_url": "",
      "thai_demo": "",
      "provider_key": "rss_npr-world"
    },
    {
      "id": "7e996bcfb29a4727f8",
      "provider": "NPR",
      "title": "U.S. lifts Iran oil sanctions. And, federal judge rules SAVE voter tool unlawful",
      "description": "The U.S. has temporarily lifted oil sanctions on Iran as peace talks continue. And, a federal judge ruled that the Trump administration's data system, known as SAVE, is unlawful.",
      "url": "https://www.npr.org/2026/06/23/g-s1-129603/up-first-newsletter-iran-oil-sanctions-trump-economy-minnesota-subpoenas-save-voter-info",
      "category": "World",
      "published": "2026-06-23T11:17:26+00:00",
      "author": "NPR",
      "content_type": "rss news summary",
      "image_url": "",
      "thai_demo": "",
      "provider_key": "rss_npr-world"
    },
    {
      "id": "117524b56cd4530cfd",
      "provider": "NPR",
      "title": "Who would pay for Trump's proposed $300 billion Iran reconstruction fund?",
      "description": "It's still unclear who would fund a proposed $300 billion reconstruction plan for Iran. Former National Security Adviser Jake Sullivan called the whole approach \"something entirely new.\"",
      "url": "https://www.npr.org/2026/06/23/nx-s1-5866577/iran-trump-deal-300-billion-obama",
      "category": "World",
      "published": "2026-06-23T10:51:02+00:00",
      "author": "NPR",
      "content_type": "rss news summary",
      "image_url": "",
      "thai_demo": "",
      "provider_key": "rss_npr-world"
    },
    {
      "id": "9004b2e42ee9321cfa",
      "provider": "NPR",
      "title": "A U.S.-Iran dispute over nuclear inspections clouds work to finalize a war-ending deal",
      "description": "As U.S.-Iran talks continued, a break in the shipping bottleneck through the Strait of Hormuz appeared to be in the works.",
      "url": "https://www.npr.org/2026/06/23/nx-s1-5867322/us-iran-finalize-war-ending-deal",
      "category": "World",
      "published": "2026-06-23T09:29:01+00:00",
      "author": "NPR",
      "content_type": "rss news summary",
      "image_url": "",
      "thai_demo": "",
      "provider_key": "rss_npr-world"
    },
    {
      "id": "dbfdb421752ed99d0d",
      "provider": "NPR",
      "title": "Meta plans to release AI-powered prediction market app, documents show",
      "description": "The company is building an app separate from Facebook and Instagram where people can wager on the outcome of real-world events, using \"play money.\"",
      "url": "https://www.npr.org/2026/06/24/nx-s1-5869486/meta-prediction-market-app-ai",
      "category": "Business",
      "published": "2026-06-24T18:39:06+00:00",
      "author": "NPR",
      "content_type": "rss news summary",
      "image_url": "",
      "thai_demo": "",
      "provider_key": "rss_npr-business"
    },
    {
      "id": "c2266b4ce3b4a397a4",
      "provider": "NPR",
      "title": "Congress passes the largest housing affordability bill in decades — and Trump cancels the signing",
      "description": "President Trump canceled a signing ceremony for the bill Wednesday, saying Congress must first pass a strict voter ID bill.",
      "url": "https://www.npr.org/2026/06/23/nx-s1-5867575/congress-passes-housing-affordability-bill",
      "category": "Business",
      "published": "2026-06-23T20:46:10+00:00",
      "author": "NPR",
      "content_type": "rss news summary",
      "image_url": "",
      "thai_demo": "",
      "provider_key": "rss_npr-business"
    },
    {
      "id": "b3d8b530226123e4cd",
      "provider": "NPR",
      "title": "Is AI 'one big bubble'? Behind the tech sell-off",
      "description": "Investors are selling off AI-related stocks as doubts are starting to surface over whether the massive spending on AI is worth the investment and whether it's \"one big bubble.\"",
      "url": "https://www.npr.org/2026/06/23/nx-s1-5867633/ai-selloff-tech-stocks-bubble-nasdaq",
      "category": "Business",
      "published": "2026-06-23T19:31:54+00:00",
      "author": "NPR",
      "content_type": "rss news summary",
      "image_url": "",
      "thai_demo": "",
      "provider_key": "rss_npr-business"
    },
    {
      "id": "1e34bf5bdfc8418505",
      "provider": "NPR",
      "title": "When falling housing prices are good news — and when they're not",
      "description": "Denver renters are celebrating falling housing costs. But sometimes cheaper housing is a sign of economic decline. How can you tell the difference?",
      "url": "https://www.npr.org/sections/planet-money/2026/06/23/g-s1-129339/when-falling-housing-prices-are-good-news-and-when-theyre-not",
      "category": "Business",
      "published": "2026-06-23T10:30:00+00:00",
      "author": "NPR",
      "content_type": "rss news summary",
      "image_url": "",
      "thai_demo": "",
      "provider_key": "rss_npr-business"
    },
    {
      "id": "5dd290490d13819631",
      "provider": "NPR",
      "title": "Why are crisis pregnancy centers saying they can 'rule out' ectopic pregnancy?",
      "description": "Under President Trump, more federal attention and support has gone towards anti-abortion Christian centers. A watchdog group says many of them mislead patients with promises to \"rule out\" ectopic pregnancies.",
      "url": "https://www.npr.org/2026/06/24/nx-s1-5860744/crisis-pregnancy-centers-ectopic-abortion",
      "category": "Health",
      "published": "2026-06-24T09:00:00+00:00",
      "author": "NPR",
      "content_type": "rss news summary",
      "image_url": "",
      "thai_demo": "",
      "provider_key": "rss_npr-health"
    },
    {
      "id": "94ff42bd9fdc1ed451",
      "provider": "NPR",
      "title": "How to protect yourself from ticks",
      "description": "It's tick season, but how do you avoid the little arachnids? NPR asks two experts in tick bites and behavior.",
      "url": "https://www.npr.org/2026/06/24/nx-s1-5836468/how-to-protect-yourself-from-ticks",
      "category": "Health",
      "published": "2026-06-24T08:39:21+00:00",
      "author": "NPR",
      "content_type": "rss news summary",
      "image_url": "",
      "thai_demo": "",
      "provider_key": "rss_npr-health"
    },
    {
      "id": "2b6e0590ea9afe5423",
      "provider": "NPR",
      "title": "Red Cross volunteers work to combat heat-related deaths at Phoenix mobile homes",
      "description": "In Phoenix, Ariz., a disproportionate number of indoor heat-related deaths happen in mobile homes. Red Cross volunteers are working to change that.",
      "url": "https://www.npr.org/2026/06/23/nx-s1-5836488-e1/red-cross-volunteers-work-to-combat-heat-related-deaths-at-phoenix-mobile-homes",
      "category": "Health",
      "published": "2026-06-23T20:41:00+00:00",
      "author": "NPR",
      "content_type": "rss news summary",
      "image_url": "",
      "thai_demo": "",
      "provider_key": "rss_npr-health"
    },
    {
      "id": "0d289c047ea32f9de6",
      "provider": "NPR",
      "title": "Trouble getting weight loss drugs covered by insurance? Here's what to know",
      "description": "If your doctor prescribes a GLP-1 medication for weight loss but your insurance won't cover it, you have options.",
      "url": "https://www.npr.org/2026/06/23/nx-s1-5793971/weight-loss-glp1-insurance-coverage",
      "category": "Health",
      "published": "2026-06-23T09:00:00+00:00",
      "author": "NPR",
      "content_type": "rss news summary",
      "image_url": "",
      "thai_demo": "",
      "provider_key": "rss_npr-health"
    },
    {
      "id": "c825ced9e666406230",
      "provider": "US National Weather Service",
      "title": "Severe Thunderstorm Watch issued June 24 at 10:19PM MDT until June 25 at 1:00AM MDT by NWS Goodland KS",
      "description": "SEVERE THUNDERSTORM WATCH 390 REMAINS VALID UNTIL 1 AM MDT /2 AM CDT/ THURSDAY FOR THE FOLLOWING AREAS IN KANSAS THIS WATCH INCLUDES 13 COUNTIES IN NORTHWEST KANSAS CHEYENNE DECATUR GRAHAM NORTON RAWLINS SHERIDAN SHERMAN THOMAS IN WEST CENTRAL KANSAS GOVE GREELEY LOGAN WALLACE WICHITA IN NEBRASKA THIS WATCH INCLUDES 3 COUNTIES IN SOUTHWEST NEBRASKA DUNDY HITCHCOCK RED WILLOW THIS INCLUDES THE CITIES OF ATWOOD, BENKELMAN, BIRD CITY, COLBY, CULBERTSON, GOODLAND, GRAINFIELD, GRINNELL, HILL CITY, HOXIE, LEOTI, MCCOOK, NORTON, OAKLEY, OBERLIN, PALISADE, QUINTER, SHARON SPRINGS, ST. FRANCIS, STRATTON NE, TRENTON, AND TRIBUNE.",
      "url": "https://api.weather.gov/alerts/urn:oid:2.49.0.1.840.0.3c2044c2c24279a31853cf971c6a07cdba721e97.002.1",
      "category": "Environment",
      "published": "2026-06-25T04:19:00+00:00",
      "author": "National Weather Service",
      "content_type": "government weather alert",
      "image_url": "",
      "thai_demo": "",
      "provider_key": "us-national-weather-service"
    },
    {
      "id": "da01ee8839e56f071f",
      "provider": "US National Weather Service",
      "title": "Severe Thunderstorm Watch issued June 24 at 10:19PM MDT until June 25 at 1:00AM MDT by NWS Goodland KS",
      "description": "THE NATIONAL WEATHER SERVICE HAS ISSUED SEVERE THUNDERSTORM WATCH 390 UNTIL 1 AM MDT THURSDAY WHICH REPLACES A PORTION OF TORNADO WATCH 389. THE NEW WATCH IS VALID FOR THE FOLLOWING AREAS IN COLORADO THE NEW WATCH INCLUDES 3 COUNTIES IN EAST CENTRAL COLORADO CHEYENNE KIT CARSON IN NORTHEAST COLORADO YUMA THIS INCLUDES THE CITIES OF ARAPAHOE, BURLINGTON, CHEYENNE WELLS, WRAY, AND YUMA.",
      "url": "https://api.weather.gov/alerts/urn:oid:2.49.0.1.840.0.3c2044c2c24279a31853cf971c6a07cdba721e97.001.2",
      "category": "Environment",
      "published": "2026-06-25T04:19:00+00:00",
      "author": "National Weather Service",
      "content_type": "government weather alert",
      "image_url": "",
      "thai_demo": "",
      "provider_key": "us-national-weather-service"
    },
    {
      "id": "8f454c70c44a33abda",
      "provider": "US National Weather Service",
      "title": "Severe Thunderstorm Warning issued June 24 at 10:15PM MDT until June 24 at 11:15PM MDT by NWS Goodland KS",
      "description": "SVRGLD The National Weather Service in Goodland has issued a * Severe Thunderstorm Warning for... Southwestern Yuma County in northeastern Colorado... * Until 1115 PM MDT. * At 1014 PM MDT, severe thunderstorms were located along a line extending from 11 miles southeast of Otis to 6 miles northeast of Arickaree School to 5 miles southeast of Anton, moving southeast at 25 mph. THESE ARE DESTRUCTIVE STORMS FOR Abarr and Joes. HAZARD...80 mph wind gusts and ping pong ball size hail. SOURCE...Radar indicated. IMPACT...Flying debris will be dangerous to those caught without shelter. Mobile homes will be heavily damaged. Expect considerable damage to roofs, windows, and vehicles. Extensive tree damage and power outages are likely. * These severe thunderstorms will remain over mainly rural areas of southwestern Yuma County, including the following locations... Joes, Abarr, Kirk, and Heartstrong.",
      "url": "https://api.weather.gov/alerts/urn:oid:2.49.0.1.840.0.14ddf7bcd2455505fc7aefd8e551f6ae942dd5ea.001.1",
      "category": "Environment",
      "published": "2026-06-25T04:15:00+00:00",
      "author": "National Weather Service",
      "content_type": "government weather alert",
      "image_url": "",
      "thai_demo": "",
      "provider_key": "us-national-weather-service"
    },
    {
      "id": "a849d3decea1762204",
      "provider": "US National Weather Service",
      "title": "Severe Thunderstorm Warning issued June 24 at 11:11PM CDT until June 24 at 11:30PM CDT by NWS Lubbock TX",
      "description": "At 1110 PM CDT, a severe thunderstorm was located 8 miles west of Abernathy, moving east at 20 mph. HAZARD...Ping pong ball size hail and 60 mph wind gusts. SOURCE...Radar indicated. IMPACT...People and animals outdoors will be injured. Expect hail damage to roofs, siding, windows, and vehicles. Expect wind damage to roofs, siding, and trees. Locations impacted include... Lubbock, Abernathy, Hale Center, Shallowater, Cotton Center, Lubbock International Airport, and New Deal.",
      "url": "https://api.weather.gov/alerts/urn:oid:2.49.0.1.840.0.3403a9be20caa3e9bef1628f8e4cd2d58d43ec93.002.1",
      "category": "Environment",
      "published": "2026-06-25T04:11:00+00:00",
      "author": "National Weather Service",
      "content_type": "government weather alert",
      "image_url": "",
      "thai_demo": "",
      "provider_key": "us-national-weather-service"
    },
    {
      "id": "7951587e3e6448341f",
      "provider": "US National Weather Service",
      "title": "Severe Thunderstorm Warning issued June 24 at 10:11PM MDT until June 24 at 11:00PM MDT by NWS Denver CO",
      "description": "SVRBOU The National Weather Service in Denver has issued a * Severe Thunderstorm Warning for... Southeastern Washington County in northeastern Colorado... * Until 1100 PM MDT. * At 1011 PM MDT, a severe thunderstorm was located 7 miles north of Arickaree School, or 24 miles southeast of Akron, moving southeast at 20 mph. THIS IS A DESTRUCTIVE STORM FOR COPE. HAZARD...80 mph wind gusts and quarter size hail. SOURCE...Radar indicated. IMPACT...Flying debris will be dangerous to those caught without shelter. Mobile homes will be heavily damaged. Expect considerable damage to roofs, windows, and vehicles. Extensive tree damage and power outages are likely. * Locations impacted include... Arickaree School and Cope.",
      "url": "https://api.weather.gov/alerts/urn:oid:2.49.0.1.840.0.cc573e5419b3048beaf81d1925ef8c7aa116a546.001.1",
      "category": "Environment",
      "published": "2026-06-25T04:11:00+00:00",
      "author": "National Weather Service",
      "content_type": "government weather alert",
      "image_url": "",
      "thai_demo": "",
      "provider_key": "us-national-weather-service"
    },
    {
      "id": "f90e837532ab689a69",
      "provider": "US National Weather Service",
      "title": "Severe Thunderstorm Warning issued June 24 at 11:10PM CDT until June 24 at 11:30PM CDT by NWS Amarillo TX",
      "description": "At 1110 PM CDT, a severe thunderstorm was located 6 miles east of Bootleg, or 15 miles north of Friona, moving east at 30 mph. HAZARD...60 mph wind gusts. SOURCE...Radar indicated. IMPACT...Minor damage to roofs, siding, and trees is possible. Locations impacted include... Hereford, Simms, and Bootleg.",
      "url": "https://api.weather.gov/alerts/urn:oid:2.49.0.1.840.0.8c25e9c4360073b1ad5266b3184199797715e92f.001.1",
      "category": "Environment",
      "published": "2026-06-25T04:10:00+00:00",
      "author": "National Weather Service",
      "content_type": "government weather alert",
      "image_url": "",
      "thai_demo": "",
      "provider_key": "us-national-weather-service"
    },
    {
      "id": "eb9a655d9298064be7",
      "provider": "US National Weather Service",
      "title": "Severe Thunderstorm Warning issued June 24 at 10:08PM MDT until June 24 at 11:00PM MDT by NWS Denver CO",
      "description": "SVRBOU The National Weather Service in Denver has issued a * Severe Thunderstorm Warning for... Northeastern Elbert County in east central Colorado... Central Arapahoe and Eastern Arapahoe County in northeastern Colorado... * Until 1100 PM MDT. * At 1008 PM MDT, a severe thunderstorm was located over Deer Trail, or 29 miles northwest of Limon, moving east at 15 mph. HAZARD...Two inch hail and 60 mph wind gusts. SOURCE...Radar indicated. IMPACT...People and animals outdoors will be injured. Expect hail damage to roofs, siding, windows, and vehicles. Expect wind damage to roofs, siding, and trees. * Locations impacted include... Deer Trail and Cottonwood Valley.",
      "url": "https://api.weather.gov/alerts/urn:oid:2.49.0.1.840.0.d6b1315d47b3ff63857a7870bad9dc0123013e52.001.1",
      "category": "Environment",
      "published": "2026-06-25T04:08:00+00:00",
      "author": "National Weather Service",
      "content_type": "government weather alert",
      "image_url": "",
      "thai_demo": "",
      "provider_key": "us-national-weather-service"
    },
    {
      "id": "5eb13364f5a7939b80",
      "provider": "US National Weather Service",
      "title": "Severe Thunderstorm Warning issued June 24 at 10:08PM MDT until June 24 at 10:45PM MDT by NWS Riverton WY",
      "description": "SVRRIW The National Weather Service in Riverton has issued a * Severe Thunderstorm Warning for... East central Fremont County in central Wyoming... * Until 1045 PM MDT. * At 1008 PM MDT, a severe thunderstorm was located over Arapahoe, which is near Riverton, moving northeast at 35 mph. HAZARD...60 mph wind gusts and half dollar size hail. Accumulating Hail. SOURCE...Radar indicated. IMPACT...Hail damage to vehicles is expected. Expect wind damage to roofs, siding, and trees. * This severe thunderstorm will be near... Riverton around 1015 PM MDT.",
      "url": "https://api.weather.gov/alerts/urn:oid:2.49.0.1.840.0.ebc0acd70ee2e081ca76b614cbc4c7213c656f78.001.1",
      "category": "Environment",
      "published": "2026-06-25T04:08:00+00:00",
      "author": "National Weather Service",
      "content_type": "government weather alert",
      "image_url": "",
      "thai_demo": "",
      "provider_key": "us-national-weather-service"
    },
    {
      "id": "f8a62a9d66fee5ebf9",
      "provider": "US National Weather Service",
      "title": "Severe Thunderstorm Warning issued June 24 at 11:06PM CDT until June 24 at 11:30PM CDT by NWS Lubbock TX",
      "description": "SVRLUB The National Weather Service in Lubbock Texas has issued a * Severe Thunderstorm Warning for... Parmer County in the Panhandle of Texas... Western Castro County in the Panhandle of Texas... * Until 1130 PM CDT. * At 1104 PM CDT, a severe thunderstorm was located 4 miles southeast of Bovina, or 13 miles southwest of Friona, moving northeast at 35 mph. HAZARD...60 mph wind gusts and quarter size hail. SOURCE...Radar indicated. IMPACT...Hail damage to vehicles is expected. Expect wind damage to roofs, siding, and trees. * Locations impacted include... Friona, Bovina, Farwell, Summerfield, Lazbuddie, Oklahoma Lane, Lariat, Rhea, and Black.",
      "url": "https://api.weather.gov/alerts/urn:oid:2.49.0.1.840.0.8b126bca6d9e21fcc4dcbe2ad556504fae1e66f7.001.1",
      "category": "Environment",
      "published": "2026-06-25T04:06:00+00:00",
      "author": "National Weather Service",
      "content_type": "government weather alert",
      "image_url": "",
      "thai_demo": "",
      "provider_key": "us-national-weather-service"
    },
    {
      "id": "aeda6f92159b1e74a8",
      "provider": "US National Weather Service",
      "title": "Special Weather Statement issued June 24 at 10:03PM MDT by NWS Albuquerque NM",
      "description": "At 1003 PM MDT, Doppler radar was tracking a line of strong thunderstorms extending from 13 miles south of Bellview to 5 miles south of Arch, moving northeast at 5 mph. HAZARD...Wind gusts of 50 to 55 mph and half inch size hail. SOURCE...Radar indicated. IMPACT...Gusty winds could knock down tree limbs and blow around unsecured objects. Minor damage to outdoor objects is possible. Locations impacted include... Clovis, Texico, Cannon Air Force Base, Ranchvale, Arch, Portair and Pleasant Hill. This includes Highway 60 between Mile Markers 381 and 397.",
      "url": "https://api.weather.gov/alerts/urn:oid:2.49.0.1.840.0.a7b352b0f8eedf342a92313121159d79e9bc0e30.001.1",
      "category": "Environment",
      "published": "2026-06-25T04:03:00+00:00",
      "author": "National Weather Service",
      "content_type": "government weather alert",
      "image_url": "",
      "thai_demo": "",
      "provider_key": "us-national-weather-service"
    },
    {
      "id": "63deb9d4b3ab121e2b",
      "provider": "USGS",
      "title": "M 6.9 - 30 km ENE of Kuji, Japan",
      "description": "The United States Geological Survey reported an earthquake of magnitude 6.9. The event occurred near 30 km ENE of Kuji, Japan. Official monitoring data may be updated as scientists review additional measurements.",
      "url": "https://earthquake.usgs.gov/earthquakes/eventpage/us6000t7zq",
      "category": "World",
      "published": "2026-06-24T22:30:14.931000+00:00",
      "author": "U.S. Geological Survey",
      "content_type": "government earthquake report",
      "image_url": "",
      "thai_demo": "",
      "provider_key": "usgs"
    },
    {
      "id": "4132739f049eda06d7",
      "provider": "USGS",
      "title": "M 7.5 - 28 km SE of Yumare, Venezuela",
      "description": "The United States Geological Survey reported an earthquake of magnitude 7.5. The event occurred near 28 km SE of Yumare, Venezuela. Official monitoring data may be updated as scientists review additional measurements.",
      "url": "https://earthquake.usgs.gov/earthquakes/eventpage/us6000t7zp",
      "category": "World",
      "published": "2026-06-24T22:05:11.566000+00:00",
      "author": "U.S. Geological Survey",
      "content_type": "government earthquake report",
      "image_url": "",
      "thai_demo": "",
      "provider_key": "usgs"
    },
    {
      "id": "dc927d03dac19a83b7",
      "provider": "USGS",
      "title": "M 7.2 - 23 km SE of Yumare, Venezuela",
      "description": "The United States Geological Survey reported an earthquake of magnitude 7.2. The event occurred near 23 km SE of Yumare, Venezuela. Official monitoring data may be updated as scientists review additional measurements.",
      "url": "https://earthquake.usgs.gov/earthquakes/eventpage/us6000t7zc",
      "category": "World",
      "published": "2026-06-24T22:04:33.389000+00:00",
      "author": "U.S. Geological Survey",
      "content_type": "government earthquake report",
      "image_url": "",
      "thai_demo": "",
      "provider_key": "usgs"
    },
    {
      "id": "08ff708dff19c5895a",
      "provider": "USGS",
      "title": "M 5.6 - 11 km N of Redwood Valley, CA",
      "description": "The United States Geological Survey reported an earthquake of magnitude 5.59. The event occurred near 11 km N of Redwood Valley, CA. Official monitoring data may be updated as scientists review additional measurements.",
      "url": "https://earthquake.usgs.gov/earthquakes/eventpage/nc75382936",
      "category": "World",
      "published": "2026-06-24T15:10:40.760000+00:00",
      "author": "U.S. Geological Survey",
      "content_type": "government earthquake report",
      "image_url": "",
      "thai_demo": "",
      "provider_key": "usgs"
    },
    {
      "id": "40411752e8ca6fa02d",
      "provider": "arXiv",
      "title": "Learning Action Priors for Cross-embodiment Robot Manipulation",
      "description": "Most Vision-Language-Action (VLA) models build on a Vision-Language Model (VLM) backbone by attaching an action module and optimizing the full policy jointly. This design inherits strong visual and linguistic priors from the VLM, but leaves the action module to learn physical motion almost from scratch. As a result, the policy lacks an explicit motion prior, forcing early optimization to simultaneously discover temporal action dynamics and cross-modal alignment, a challenge further amplified in cross-embodiment settings. In this work, we propose to pretrain the action module with motion priors before cross-modal VLA alignment. Specifically, we introduce a two-stage training framework that equips the action module with cross-embodiment temporal motion structure before VLA training begins. In Stage~1, a lightweight flow-matching-based encoder-decoder action module efficiently learns temporal motion structure solely from unconditioned action trajectories, without processing visual or language tokens. In Stage~2, this learned prior is transferred to VLA training through decoder reuse and early-stage latent distillation, aligning visual-language features with the action embedding space while still allowing end-to-end policy refinement. In addition, the trained encoder serves as a compact history compressor, summarizing state-action histories into a single temporal context token for history-aware modeling at negligible cost. Extensive experiments across 13 diverse cross-embodiment tasks on both simulated and real-world platforms validate the effectiveness of our approach. Compared with VLA training without action priors, our model achieves faster convergence, higher success rates, and substantially stronger performance on data-scarce real-world tasks. Moreover, scaling up the action data in Stage~1 yields a more generalizable action prior that directly improves downstream VLA performance.",
      "url": "http://arxiv.org/abs/2606.26095v1",
      "category": "Technology",
      "published": "2026-06-24T17:59:56+00:00",
      "author": "Dong Jing, Tianqi Zhang, Jiaqi Liu, Jinman Zhao, Zelong Sun, Li Erran Li, Zhiwu Lu, Mingyu Ding",
      "content_type": "research summary",
      "image_url": "",
      "thai_demo": "",
      "provider_key": "arxiv"
    },
    {
      "id": "e5551c6f521bfc756a",
      "provider": "arXiv",
      "title": "ForceBand: Learning Forceful Manipulation with sEMG",
      "description": "Human demonstrations are a scalable data source for learning robot manipulation policies. However, common sources of human demonstration data, such as motion-capture trajectories and internet videos, capture mostly motion and appearance while missing the contact forces that are critical for force-sensitive manipulation. In this paper, we introduce ForceBand, a low-cost wrist-worn sEMG system that turns human muscle activity into force-enriched demonstrations. We first collect a 10-hour multimodal dataset containing egocentric video, sEMG, IMU, and fingertip force measurements across diverse actions and objects. Using this dataset, we pre-train an EMG2Force model that predicts per-finger forces from sEMG and IMU signals. After a short user-specific calibration, users can collect target-task demonstrations using only ForceBand and video; EMG2Force then labels these demonstrations with per-finger force traces, producing force-augmented demonstrations for robot policy learning. Experiments show that ForceBand recovers fine-grained fingertip interactions with over 50% lower force prediction error than vision-based baselines and achieves an 87% success rate on pick, squeeze, and place tasks that require object-specific force control across objects with diverse shapes, sizes, and weights. Project website: https://forceband-emg.github.io",
      "url": "http://arxiv.org/abs/2606.26093v1",
      "category": "Technology",
      "published": "2026-06-24T17:59:35+00:00",
      "author": "Botao He, Zhi Wang, Linna Kuang, Ishaan Ghosh, Jitendra Malik, Cornelia Fermuller, Tingfan Wu, Jiayuan Mao, Ruoshi Liu, Haozhi Qi, Yiannis Aloimonos",
      "content_type": "research summary",
      "image_url": "",
      "thai_demo": "",
      "provider_key": "arxiv"
    },
    {
      "id": "d6a4b921271195e9d0",
      "provider": "arXiv",
      "title": "On-Policy Self-Distillation with Sampled Demonstrations Reduces Output Diversity",
      "description": "On-policy self-distillation achieves strong pass@1 accuracy by using a single model as both teacher and student, with the teacher conditioned on a correct demonstration to provide dense token-level feedback. We show that this could come at a hidden cost: rollout diversity decreases and pass@k curves flatten (i.e., generating more rollouts fails to improve accuracy). We trace this to compounding biases in the design of self-distillation with sampled demonstrations. The teacher scores each student rollout while conditioned on a sampled correct rollout, channeling its feedback through the model's own biases. We theoretically analyze the optimal self-distillation policy and show that it tilts the base distribution by a pointwise conditional mutual information score between the student's rollout and the correct rollout used as context. Unlike the ideal optimal on-policy reinforcement learning (RL), which preserves probability ratios among equally correct rollouts, self-distillation can amplify existing probability gaps, concentrating mass on already-dominant modes. On a controlled graph path-finding task and science question-answering benchmarks, self-distilled models match or exceed RL on average performance but exhibit substantially lower functional and semantic diversity, failing on out-of-distribution settings that require diverse strategies.",
      "url": "http://arxiv.org/abs/2606.26091v1",
      "category": "Technology",
      "published": "2026-06-24T17:59:02+00:00",
      "author": "Andrei Liviu Nicolicioiu, Mohammad Pezeshki, Aaron Courville",
      "content_type": "research summary",
      "image_url": "",
      "thai_demo": "",
      "provider_key": "arxiv"
    },
    {
      "id": "7534bbde5e1331cb67",
      "provider": "arXiv",
      "title": "Real-Time Voice AI Hears but Does Not Listen",
      "description": "Speech conveys information through both words and vocal delivery. We evaluate four leading production realtime voice systems-OpenAI's GPT Realtime 2, Google's Gemini 3.1 Flash Live, and Alibaba's Qwen3.5 Omni Plus and Omni Flash-on tasks where the words and the delivery patterns both convey meaningful information. Across three consequential scenarios, all four systems act on the words rather than the voice. They end calls with crying callers who insist nothing is wrong, approve wire transfers authorized in frightened voices, and enroll callers whose agreement is clearly sarcastic. Surprisingly, this is often not a failure of perception. When asked directly, three of the four systems reliably identify the distress, fear, or sarcasm they later ignore when making decisions. We observe a similar pattern when these realtime voice systems estimate accent and age, as their responses frequently follow the biases of the words rather than the acoustic properties of the speaker. We term this disconnect between perception and action the emotional intelligence gap of voice AI. Prompting systems to explicitly attend to vocal delivery improves performance only partially and inconsistently. Our findings show that current realtime voice AI systems often behave as if speech had been reduced to a transcript, suggesting that they should be used with caution in settings where the tone and emotion of delivery convey important information.",
      "url": "http://arxiv.org/abs/2606.26083v1",
      "category": "Technology",
      "published": "2026-06-24T17:55:38+00:00",
      "author": "Martijn Bartelds, Federico Bianchi, James Zou",
      "content_type": "research summary",
      "image_url": "",
      "thai_demo": "",
      "provider_key": "arxiv"
    },
    {
      "id": "fa23100c635daea751",
      "provider": "arXiv",
      "title": "Neglected Free Lunch from Post-training: Progress Advantage for LLM Agents",
      "description": "Process reward models enable fine-grained, step-level evaluation of LLMs, yet building them for agentic settings remains prohibitively difficult: long-horizon interactions, irreversible actions, and stochastic environment feedback make both human annotation and Monte Carlo estimation infeasible at scale. In this work, we show that reinforcement learning (RL) post-training already provides the ingredients for effective step-level scoring, eliminating the need for dedicated reward model training altogether. Concretely, we derive an implicit advantage under a general stochastic Markov decision process, which we term progress advantage -- log-probability ratio between the RL-trained policy and its reference policy exactly recovers the optimal advantage function. This formulation makes the resulting signal annotation-free, domain-agnostic, and available as a byproduct of the standard RL post-training pipeline. We validate the effectiveness of the progress advantage across three different applications: test-time scaling, uncertainty quantification, and failure attribution on five benchmarks and four model families. Across all settings, it consistently outperforms confidence-based baselines and, despite requiring no task-specific training, surpasses dedicated trained reward models. We complement these results with deeper analyses on characteristics of progress advantage, offering practical guidance for adoption in real-world agentic systems.",
      "url": "http://arxiv.org/abs/2606.26080v1",
      "category": "Technology",
      "published": "2026-06-24T17:54:08+00:00",
      "author": "Changdae Oh, Wendi Li, Seongheon Park, Samuel Yeh, Tanwi Mallick, Sharon Li",
      "content_type": "research summary",
      "image_url": "",
      "thai_demo": "",
      "provider_key": "arxiv"
    },
    {
      "id": "d22c73e21e595540b2",
      "provider": "arXiv",
      "title": "Same Evidence, Different Answer: Auditing Order Sensitivity in Multimodal Large Language Models",
      "description": "Standard benchmarks for multimodal large language models (MLLMs) score each item on one canonical ordering and miss whether order-irrelevant shuffling changes the answer, a baseline reliability property called for by emerging AI evaluation guidelines. We introduce Facet-Probe, a five-facet audit (option, evidence-chunk, document-rank, image-set, and mixed-modality ordering) of 18 frontier and open-weight MLLMs. A Bayesian item-response model separates ordering noise from per-facet bias, and a same-ordering control estimates the decoder-stochastic floor for observed flips. We find that none of the 18 MLLMs we audit are order-invariant: screened per-facet panel-mean flip rates span 24-50%. A Gemini same-ordering control at temperature 0 estimates a substantial ordering excess over a same-input decoder-noise floor in verified cells. Capability predicts but does not eliminate flips; the best model still flips on 13.4% of trials. In our Gemini mitigation tests, training-free prompt changes are modality-conditional and do not transfer from text to visual reasoning. These results suggest that prompt-level mitigation alone is unlikely to provide general order robustness, motivating future work on training-time and architectural approaches. We propose cross-ordering flip rate as a standard reporting axis for MLLMs.",
      "url": "http://arxiv.org/abs/2606.26079v1",
      "category": "Technology",
      "published": "2026-06-24T17:53:26+00:00",
      "author": "Akshay Paruchuri, Sanmi Koyejo, Ehsan Adeli",
      "content_type": "research summary",
      "image_url": "",
      "thai_demo": "",
      "provider_key": "arxiv"
    },
    {
      "id": "e663badd6c31eb13ce",
      "provider": "arXiv",
      "title": "A cross-process welding penetration status prediction algorithm based on unsupervised domain adaptation in laser and TIG welding",
      "description": "Supervised deep learning has been widely used for weld penetration state classification; however, its performance often degrades significantly under domain shift, such as when transferring models between welding processes with distinct physical mechanisms:for instance, from arc-dominated tungsten inert gas (TIG) welding to keyhole-based laser welding. To overcome this limitation, we propose an unsupervised domain adaptation (UDA) framework integrated with a gradual source domain expansion (GSDE) strategy. Evaluated on dedicated TIG and laser welding datasets, our approach achieves high accuracy in both same-process and cross-process transfer tasks. Specifically, it attains average accuracies of 90.65% on TIGFH and 90.72% on LSPS in same-process settings, surpassing a supervised baseline by 35.83% and 38.87%, respectively. More notably, in cross-process scenarios, it reaches 80.48% for TIG to Laser and 81.13% for Laser to TIG, improving upon the baseline by 43.39% and 43.40%. UMAP visualizations verify that the model learns domain-invariant features while maintaining discriminative class boundaries. This method considerably lowers the relabeling cost for new welding processes and enhances the versatility of intelligent monitoring across different welding systems.",
      "url": "http://arxiv.org/abs/2606.26078v1",
      "category": "Technology",
      "published": "2026-06-24T17:52:57+00:00",
      "author": "Sen Li, Haichao Cui, Chendong Shao, Yaqi Wang, Xinhua Tang",
      "content_type": "research summary",
      "image_url": "",
      "thai_demo": "",
      "provider_key": "arxiv"
    },
    {
      "id": "5a4be46b407c790027",
      "provider": "arXiv",
      "title": "Model Forensics: Investigating Whether Concerning Behavior Reflects Misalignment",
      "description": "A central goal of safety research is determining whether a model is misaligned. Prior work has largely focused on detecting concerning behavior. But behavior alone does not establish misalignment: a concerning action can arise from benign causes such as confusion. This motivates model forensics: investigating whether the action was driven by malign intent. In this paper, we propose a baseline protocol for model forensics consisting of two steps, iterated as needed. First, we read the chain of thought (CoT) to generate hypotheses about what drives model behavior. Second, we make edits to the prompt or environment to test these hypotheses. While the CoT is not always faithful, it is a rich source of unsupervised insight that can guide the collection of more rigorous evidence. To evaluate our protocol, we create a suite of six agentic environments where models exhibit concerning behavior, and apply it to each. We establish that Kimi K2 Thinking takes shortcuts due to a genuine disposition towards low-effort actions, by showing this hypothesis successfully predicts its behavior. Through counterfactual experiments, we show DeepSeek R1 deceives out of a desire to be consistent with a previous instance of itself. Our methods nonetheless leave significant room for refinement. For example, when we test whether Kimi K2 Thinking believes it is violating user intent, we find no evidence of such a belief, but without positive controls we cannot confirm our tests would detect it. Overall, we find our simple protocol provides a strong baseline that we hope future work will improve upon. More broadly, our work is a concrete step in developing the growing field of model forensics.",
      "url": "http://arxiv.org/abs/2606.26071v1",
      "category": "Technology",
      "published": "2026-06-24T17:45:47+00:00",
      "author": "Aditya Singh, Gerson Kroiz, Senthooran Rajamanoharan, Neel Nanda",
      "content_type": "research summary",
      "image_url": "",
      "thai_demo": "",
      "provider_key": "arxiv"
    },
    {
      "id": "6d9ff4389ec54b7410",
      "provider": "arXiv",
      "title": "When Certainty Is an Artifact: Keyword Lexicon Blindness and the (Mis)Measurement of Rhetorical Stance",
      "description": "Can a statistically significant, large-effect-size finding in computational social science be entirely an artifact of the measurement instrument? We present a case where the answer appears to be yes. Analyzing 85 interviews across four public intellectuals (2016--2026), we find a robust negative-affect/emphatic-certainty lexical co-occurrence pattern under keyword-based scoring ($r = 0.72$--$0.93$, $p < 0.01$ for all four speakers). Replacing keyword counting with LLM-based zero-shot semantic classification on the complete diarized corpus (32,625 sentences) dramatically reduces this correlation: Dalio's $r = 0.851$ drops to $r = 0.206$, with two speakers showing negative $r(\\text{neg}, \\text{emphatic})$ and one showing null. In contrast, the LLM reveals a strong negative-hedging coupling across speakers -- Rogoff's $r(\\text{neg}, \\text{hedged}) = 0.875$ ($p = 0.001$) and Zeihan's $r(\\text{neg}, \\text{hedged}) = 0.722$ ($p = 0.008$) -- consistent with the conventional expectation that pessimistic discourse attracts hedging, not certainty. Sentence-level error analysis traces this discrepancy to three structural failure modes in keyword lexicons -- syntactic blindness, polysemy blindness, and categorical absence -- illustrated through cases where keyword counting inverts semantic meaning (e.g., ''never absolutely totally confident'' scored as high-certainty). We argue that keyword lexicons measure a universal lexical co-occurrence tendency -- negative discourse naturally attracts emphatic vocabulary -- that is orthogonal to, and can systematically invert, rhetorical stance. Treating keyword counts as measurements of epistemic certainty is a category error: a finding that appears to be about a speaker's psychology may be entirely about the counting of words.",
      "url": "http://arxiv.org/abs/2606.26062v1",
      "category": "Technology",
      "published": "2026-06-24T17:36:39+00:00",
      "author": "Bo Chen",
      "content_type": "research summary",
      "image_url": "",
      "thai_demo": "",
      "provider_key": "arxiv"
    },
    {
      "id": "143538794970b8ef9e",
      "provider": "arXiv",
      "title": "A welding penetration prediction model for laser welding process based on self-supervised learning using physics-informed neural networks",
      "description": "The laser welding full-penetration is of critical importance, as it constitutes one of the fundamental factors in achieving defect-free welded joints. Accurate prediction of the penetration state is therefore essential for ensuring weld quality. To this end, this paper introduces SimPhysNet, a novel algorithm that achieves high classification accuracy in laser welding penetration prediction using only a limited number of labelled images. This approach effectively overcomes the limitations of supervised learning classification algorithms, which are hindered in industrial applications by their dependence on extensive, high-quality labelled data. The core of SimPhysNet is a unique self-supervised learning paradigm that embeds physical priors into a contrastive learning framework. By incorporating a physics-informed neural network (PINN), the model is guided to extract physically meaningful features of the molten pool and keyhole from a large set of unlabelled data, while three image augmentation tasks further enhance its generalization capabilities. Subsequently, a few-shot learning strategy, based on prototypical networks, enables robust classification by constructing class representations from a minimal set of labelled images. Experimental results demonstrate that SimPhysNet achieves a classification accuracy of 96.06% using only 200 labelled images (approximately 5% of the total labelled dataset), which is comparable to the performance of conventional supervised learning algorithms that utilize the entire labelled dataset. This work presents a new, efficient, and highly accurate method, providing the way for the intelligent automation of laser welding.",
      "url": "http://arxiv.org/abs/2606.26059v1",
      "category": "Technology",
      "published": "2026-06-24T17:33:41+00:00",
      "author": "Sen Li, Xiaoying Liu, Xiaojian Xu, Chendong Shao, Yaqi Wang, Ling Lan, Xinhua Tang, Haichao Cui",
      "content_type": "research summary",
      "image_url": "",
      "thai_demo": "",
      "provider_key": "arxiv"
    },
    {
      "id": "f545e4425018a87d36",
      "provider": "arXiv",
      "title": "The Unfireable Safety Kernel: Execution-Time AI Alignment for AI Agents and Other Escapable AI Systems",
      "description": "AI agents are granted access to tools, APIs, and other infrastructure, making them active principals in those systems. The dominant approach places controls inside the agent's own runtime: system prompts, output filters, and guardrail libraries. Any control in the agent's address space is reachable by inputs that influence it; this generalizes to any AI system with sufficient reach into its own runtime, a class we term escapable AI systems. We identify four properties that an authorization mechanism must satisfy for architectural control rather than for cooperative requests: process separation, pre-action enforcement on a structurally only path, fail-closed at both the request and system levels, and externalized signed evidence verifiable outside the controlled system's trust boundary. We position this layer as execution-time AI alignment, complementing training-time alignment (RLHF, Constitutional AI) and inference-time alignment. We present the Unfireable Safety Kernel, a Rust reference implementation realizing all four. Its fail-closed invariant is machine-checked at two levels: an SMT theorem (Z3) and an exhaustive bounded-model-checking proof of the production decision function (Kani, 4/4 harnesses). A Python-to-Rust migration was gated on byte-equivalence (1000/1000 fixtures; 17/17 adversarial classes). We evaluate the kernel governing a live, escapable AI system, a deterministic, self-improving world model, against an escape-seeking adversary driving its real self-modification seam: across 1,000 self-modifications, all 704 attempts on the safety-critical core are refused, with no escape; a further 300, under the operator kill switch, are also refused. A separate campaign of 6,240 authorization round-trips had no successful bypass. Against 3 contemporary systems claiming the agent control plane, the agent invokes control; here, it lacks that choice.",
      "url": "http://arxiv.org/abs/2606.26057v1",
      "category": "Technology",
      "published": "2026-06-24T17:32:27+00:00",
      "author": "Seth Dobrin, Łukasz Chmiel",
      "content_type": "research summary",
      "image_url": "",
      "thai_demo": "",
      "provider_key": "arxiv"
    },
    {
      "id": "9afc678b7e8b9bf75c",
      "provider": "arXiv",
      "title": "Natural Ungrokking: Asymmetric Control of Which Rules Survive Pretraining",
      "description": "Midway through an ordinary pretraining run, a small language model learns the pronoun-gender rule: cued with a girl's name (\"Sue cried because\"), it resolves the next pronoun to she, generalizing to held-out probes (0.94 by step 925). By step 3,500 the same model scores near zero on the same probes, although the rule's evidence is still in the training data. We call this within-run reversal natural ungrokking: the corpus decides, with no trace in the loss curve, which learned rules a model keeps. Which rules survive is predictable from one corpus statistic: how often the training stream shows the rule winning. Across un-intervened runs (two corpora, three budgets, three seeds), support frequency decides a rule's fate; the data-to-parameter ratio only modulates how deeply a doomed rule falls. The same emerge-then-collapse dynamics appear in public Pythia checkpoints, collapse depth ordered by model scale as predicted. The forgetting is a displacement: a competing surface pattern out-competes the rule, and the log-probability margin between them crosses zero within 100 training steps of the behavioral collapse. Control over this fate is asymmetric: the same edit that destroys a rule on demand cannot restore it. Flipping support to counter-evidence in place kills the rule with monotone dose-response in two unrelated rules; but injecting support back, even to 450 times the level that naturally sustains it, buys no recovery. Every confirmatory threshold and prediction was pre-registered before the data it governed was read.",
      "url": "http://arxiv.org/abs/2606.26050v1",
      "category": "Technology",
      "published": "2026-06-24T17:27:13+00:00",
      "author": "Juliana Li, Diya Sreedhar",
      "content_type": "research summary",
      "image_url": "",
      "thai_demo": "",
      "provider_key": "arxiv"
    }
  ]
}