{
  "schema_version": 5,
  "id": "f28e2c35d5fecc9bb3",
  "slug": "live-with-a-partner-you-may-be-sharing-more-microbes-than-you-think-f28e2c35",
  "level": "B1",
  "title": "Live with a partner? You may be sharing more microbes than you think",
  "description": "A large study finds you may share about a quarter of your oral and gut microbes with the people you live with. Should you worry? We asked the experts.",
  "text": "A lot changes when you move in with your partner. when you go to bed, what you eat for breakfast, and. Possibly your microbiome. the mishmash of bacteria that live in and on you. A study published this week in Cell Press Blue finds that cohabitating romantic partners share about 44% of. Their oral microbiome and 19% of their gut microbiome. First author and computational biologist Vitor Heidrich of the University of Trento, Italy says that his lab was. Investigating potential sources of the microbes inside us \"because before birth we don't have a microbiome, so. They must be coming from somewhere.\" Previous evidence has existed that people who live together share microbiomes. But the new study. which analyzed microbiome DNA data of 430 people across 207 households in Italy and. Fiji. quantifies the transmission rate by relationship and includes the oral microbiome as well.",
  "thai_text": "ข่าวนี้มาจาก NPR อยู่ในหมวดสุขภาพ และถูกเรียบเรียงเป็นระดับ B1. หัวข้อข่าวคือ “Live with a partner? You may be sharing more microbes than you think”. โดยรวมแล้ว ข่าวนี้พูดถึงประเด็นด้านสุขภาพ การแพทย์ หรือคุณภาพชีวิต ผู้อ่านควรจับใจความว่าเกิดอะไรขึ้น ใครได้รับผลกระทบ และเรื่องนี้อาจเปลี่ยนสถานการณ์ต่อไปอย่างไร. ตัวเลขที่ควรสังเกตในข่าวนี้คือ 44, 19, 430, 207. คำสำคัญที่ควรรู้: across = คำว่า across / analyzed = คำว่า analyzed / asked = ถาม / author = คำว่า author / bacteria = คำว่า bacteria.",
  "word_translations": {
    "a": "คำว่า a",
    "about": "เกี่ยวกับ",
    "across": "คำว่า across",
    "analyzed": "คำว่า analyzed",
    "and": "คำว่า and",
    "as": "คำว่า as",
    "author": "คำว่า author",
    "bacteria": "คำว่า bacteria",
    "be": "คำว่า be",
    "because": "คำว่า because",
    "bed": "คำว่า bed",
    "before": "ก่อน",
    "biologist": "คำว่า biologist",
    "birth": "คำว่า birth",
    "blue": "คำว่า blue",
    "breakfast": "คำว่า breakfast",
    "but": "คำว่า but",
    "by": "คำว่า by",
    "cell": "คำว่า cell",
    "changes": "คำว่า changes",
    "cohabitating": "คำว่า cohabitating",
    "coming": "คำว่า coming",
    "computational": "คำว่า computational",
    "data": "ข้อมูล",
    "dna": "คำว่า dna",
    "don't": "คำว่า don't",
    "eat": "คำว่า eat",
    "evidence": "คำว่า evidence",
    "existed": "คำว่า existed",
    "fiji": "คำว่า fiji",
    "finds": "พบ",
    "first": "คำว่า first",
    "for": "คำว่า for",
    "from": "คำว่า from",
    "go": "คำว่า go",
    "gut": "คำว่า gut",
    "has": "คำว่า has",
    "have": "คำว่า have",
    "heidrich": "คำว่า heidrich",
    "his": "คำว่า his",
    "households": "คำว่า households",
    "in": "คำว่า in",
    "includes": "คำว่า includes",
    "inside": "คำว่า inside",
    "investigating": "คำว่า investigating",
    "italy": "อย่างita",
    "lab": "คำว่า lab",
    "live": "คำว่า live",
    "lot": "คำว่า lot",
    "microbes": "คำว่า microbes",
    "microbiome": "คำว่า microbiome",
    "microbiomes": "คำว่า microbiomes",
    "mishmash": "คำว่า mishmash",
    "move": "ย้าย",
    "must": "คำว่า must",
    "new": "ใหม่",
    "of": "คำว่า of",
    "on": "คำว่า on",
    "oral": "คำว่า oral",
    "partner": "คำว่า partner",
    "partners": "คำว่า partners",
    "people": "ผู้คน",
    "possibly": "อย่างpossib",
    "potential": "คำว่า potential",
    "press": "คำว่า press",
    "previous": "คำว่า previous",
    "published": "คำว่า published",
    "quantifies": "คำว่า quantifies",
    "rate": "อัตรา",
    "relationship": "คำว่า relationship",
    "romantic": "คำว่า romantic",
    "says": "คำว่า says",
    "share": "แบ่งปัน",
    "so": "คำว่า so",
    "somewhere": "คำว่า somewhere",
    "sources": "คำว่า sources",
    "study": "การศึกษา",
    "that": "คำว่า that",
    "the": "คำว่า the",
    "their": "คำว่า their",
    "they": "คำว่า they",
    "this": "คำว่า this",
    "to": "คำว่า to",
    "together": "คำว่า together",
    "transmission": "เรื่อง/ภาวะของ transmission",
    "trento": "คำว่า trento",
    "university": "เรื่อง/ภาวะของ university",
    "us": "คำว่า us",
    "vitor": "คำว่า vitor",
    "was": "คำว่า was",
    "we": "คำว่า we",
    "week": "สัปดาห์",
    "well": "คำว่า well",
    "what": "คำว่า what",
    "when": "คำว่า when",
    "which": "คำว่า which",
    "who": "คำว่า who",
    "with": "คำว่า with",
    "you": "คำว่า you",
    "your": "คำว่า your"
  },
  "category": "Health",
  "provider": "NPR",
  "word_pos": {
    "a": "det.",
    "about": "prep.",
    "across": "n.",
    "analyzed": "v.",
    "and": "conj.",
    "as": "n.",
    "author": "n.",
    "bacteria": "n.",
    "be": "v.",
    "because": "conj.",
    "bed": "v.",
    "before": "prep.",
    "biologist": "n.",
    "birth": "n.",
    "blue": "n.",
    "breakfast": "n.",
    "but": "conj.",
    "by": "prep.",
    "cell": "n.",
    "changes": "n.",
    "cohabitating": "v.",
    "coming": "v.",
    "computational": "adj.",
    "data": "n.",
    "dna": "n.",
    "don't": "n.",
    "eat": "n.",
    "evidence": "n.",
    "existed": "v.",
    "fiji": "n.",
    "finds": "n.",
    "first": "n.",
    "for": "prep.",
    "from": "prep.",
    "go": "v.",
    "gut": "n.",
    "has": "n.",
    "have": "v.",
    "heidrich": "n.",
    "his": "n.",
    "households": "n.",
    "in": "prep.",
    "includes": "n.",
    "inside": "n.",
    "investigating": "v.",
    "italy": "adv.",
    "lab": "n.",
    "live": "adj.",
    "lot": "n.",
    "microbes": "n.",
    "microbiome": "n.",
    "microbiomes": "n.",
    "mishmash": "n.",
    "move": "v.",
    "must": "n.",
    "new": "adj.",
    "of": "prep.",
    "on": "prep.",
    "oral": "adj.",
    "partner": "n.",
    "partners": "n.",
    "people": "n.",
    "possibly": "adv.",
    "potential": "adj.",
    "press": "n.",
    "previous": "adj.",
    "published": "v.",
    "quantifies": "n.",
    "rate": "v.",
    "relationship": "n.",
    "romantic": "adj.",
    "says": "n.",
    "share": "n.",
    "so": "conj.",
    "somewhere": "n.",
    "sources": "n.",
    "study": "n.",
    "that": "det.",
    "the": "det.",
    "their": "n.",
    "they": "pron.",
    "this": "det.",
    "to": "prep.",
    "together": "n.",
    "transmission": "n.",
    "trento": "n.",
    "university": "n.",
    "us": "pron.",
    "vitor": "n.",
    "was": "n.",
    "we": "pron.",
    "week": "n.",
    "well": "n.",
    "what": "n.",
    "when": "v.",
    "which": "pron.",
    "who": "pron.",
    "with": "prep.",
    "you": "pron.",
    "your": "n."
  },
  "content_type": "rss news summary",
  "source_url": "https://www.npr.org/2026/06/16/nx-s1-5859419/microbiome-oral-gut-romantic-partner",
  "author": "NPR",
  "published": "2026-06-16T16:05:44+00:00",
  "published_date": "2026-06-12",
  "image": {
    "local_filename": "news-fallback.svg",
    "credit": "Local fallback",
    "credit_url": ""
  },
  "audio_cache_path": "data/audio/2026-06-12/f28e2c35d5fecc9bb3-b1.wav",
  "generated_at": "2026-06-18T05:46:35.001137+00:00"
}